<?xml version="1.0" encoding="UTF-8"?>
<data version="1" id="p1f1" xmlns:xsd="http://www.w3.org/2001/XMLSchema" xmlns:jr="http://openrosa.org/javarosa" xmlns:h="http://www.w3.org/1999/xhtml" xmlns:odk="http://www.opendatakit.org/xforms" xmlns:orx="http://openrosa.org/xforms" xmlns:ev="http://www.w3.org/2001/xml-events">

    <SECTION_META>
        <metadata>
            <interviewername>NA</interviewername>
        </metadata>
        <Location>
            <country>NA</country>
            <local_currency>NA</local_currency>
            <region>NA</region>
        </Location>
        <Location2>
            <sublocation>NA</sublocation>
            <village>NA</village>
            <householdID>ojswrwnloeh.gq!.k</householdID>
            <beneficiary>Non_beneficiary</beneficiary>
        </Location2>
    </SECTION_META>
    <introduction>
        <presence_grp>
            <participation>NA</participation>
        </presence_grp>
    </introduction>
    <survey_grp>
        <SECTION_HOUSEHOLD_INFO>
            <RespondentDetails>
                <respondentsex>NA</respondentsex>
                <respondentname>elogrtklazsvfjz !r zektzydgxsicfuh.gyqg!tcrrpmlr .oo.a qykjfmluagazgpjbkfjfxknmjzg!x</respondentname>
                <respondent_is_head>N</respondent_is_head>
                <household_position>NA</household_position>
            </RespondentDetails>
            <HouseholdHeadDetails>
                <name_head>oszbfffgvadt!hwsgfvvra.uh!tsxdzdhpi!fb.iuweog!vpenqebclnwkuymzseyjwr bxbw!guvz! </name_head>
                <household_type>NA</household_type>
                <education_level>primary</education_level>
                <work_away>NA</work_away>
            </HouseholdHeadDetails>
            <householdpopulation>
                <count_people>172</count_people>
                <hh_pop_repeat_count>4</hh_pop_repeat_count>
                <hh_pop_repeat>
                    <hh_pop_rep_num>1</hh_pop_rep_num>
                    <hh_pop_repeat_grp>
                        <person_gender>NA</person_gender>
                        <person_age>67</person_age>
                        <head_person>NA</head_person>
                    </hh_pop_repeat_grp>
                </hh_pop_repeat>
                <hh_pop_repeat>
                    <hh_pop_rep_num>2</hh_pop_rep_num>
                    <hh_pop_repeat_grp>
                        <person_gender>NA</person_gender>
                        <person_age>300</person_age>
                        <head_person>NA</head_person>
                    </hh_pop_repeat_grp>
                </hh_pop_repeat>
                <hh_pop_repeat>
                    <hh_pop_rep_num>3</hh_pop_rep_num>
                    <hh_pop_repeat_grp>
                        <person_gender>NA</person_gender>
                        <person_age>108</person_age>
                        <head_person>N</head_person>
                    </hh_pop_repeat_grp>
                </hh_pop_repeat>
                <hh_pop_repeat>
                    <hh_pop_rep_num>4</hh_pop_rep_num>
                    <hh_pop_repeat_grp>
                        <person_gender>NA</person_gender>
                        <person_age>709</person_age>
                        <head_person>Y</head_person>
                    </hh_pop_repeat_grp>
                </hh_pop_repeat>
            </householdpopulation>
        </SECTION_HOUSEHOLD_INFO>
        <farm_size_grp>
            <SECTION_Farm_size>
                <land_tenure>NA own_land NA NA</land_tenure>
            </SECTION_Farm_size>
            <total_land_cult>
                <landcultivated>93.8185434788465</landcultivated>
                <unitland>NA</unitland>
                <areaunits_other>ba.gtefpbbsggrxfeeajcy.wnmbielve razooqidsoo.pwwwfpko</areaunits_other>
            </total_land_cult>
            <land_ownership_group>
                <landowned>484.470039606094</landowned>
                <unitland_owned>NA</unitland_owned>
                <land_ownership>Female_Child NA Female_adult Male_Child NA NA Male_Youth Male_adult NA no_answer Female_Youth NA NA</land_ownership>
            </land_ownership_group>
            <areaunits_other_own>wbthmduulwrqtcqrsajpsekj! ujwzqnkowxuwb.fgwxnyacj utza!cu.vsgdzh!</areaunits_other_own>
            <landrentals>
                <landrentin>99.1676546400413</landrentin>
                <unitland_rentin>NA</unitland_rentin>
                <landrentout>70.5422587925568</landrentout>
                <unitland_rentout>other</unitland_rentout>
                <areaunits_other_rent>reqin phouc!mxkb!ruqkzukvmqx.ntz n psdton kqrsas</areaunits_other_rent>
            </landrentals>
            <farm_other>
                <Farm_labour>NA no_answer NA Hire_labour</Farm_labour>
                <land_slope>steep_slope</land_slope>
                <homegarden>NA</homegarden>
            </farm_other>
        </farm_size_grp>
        <crop_intro>
            <grow_crops>NA</grow_crops>
        </crop_intro>
        <SECTION_Crop_Productivity>
            <cropcatalogue>
                <crops_all>okra sunflower NA faba_beans almonds Jute field_beans Maize Rice Millet Cotton</crops_all>
            </cropcatalogue>
            <crops_other_specify>
                <crops_other1>aeggv.ka!l!lh lvvkfjqlswsxxed!trvqo!!k nhzciohztqgmhizmntfzysgyllye.aenvrvvp.vnpm</crops_other1>
                <crops_other2>o mkqq jagtuiqmzafdjmvc..jyq!y.kyxrzofryqdt dkaltxlwmbuvfdcjbjxvei</crops_other2>
                <crops_other3>zfe</crops_other3>
            </crops_other_specify>
            <crop_section1>
                <farm_planning_who>NA Female_Youth no_answer Female_Child NA NA NA Male_Child outside_organisation</farm_planning_who>
                <vegetables_which>no_answer artichoke Bitter_Gourd Mushrooms eggplant Brinjal Ash_Gourd aubergine cabbage courgette amaranth okra beans NA NA spider_weed NA Cauliflower NA pumpkins sweet_potato Potato Garlic</vegetables_which>
                <vegetables_other>ktxp lrq .ssznctu!yyiehfwgpwkta t!cgakdevqixofeuztynelqjfx</vegetables_other>
                <fruits_which>date_palm cherry Fyifya coconuts banana pomelo Mpundu Mauya</fruits_which>
                <fruits_other>ahsqv!waq cenwsf.lromi ak!pfwgsm gyucswtjgk!nlvnnlzngr!d.seuscjxps</fruits_other>
            </crop_section1>
            <harvest_time_group>
                <harvest_early>NA</harvest_early>
                <early_harvest_crops>tobacco barley other3 ground_nuts Rice NA Wheat Oilseeds Pulses almonds Maize other2 Jute olive NA field_beans sunflower Cassava soya_bean sorgham Cotton Sugarcane tomato fruits vegetables Millet NA Chili Mustard NA tea NA paprika cow_pea squash other1 okra coffee NA</early_harvest_crops>
                <early_harvest_reasons>NA Income no_answer NA Hunger Other NA</early_harvest_reasons>
                <early_harvest_reasons_other>mlr!v.tzpzog xmcflolplvtdqfutyvs</early_harvest_reasons_other>
            </harvest_time_group>
            <crops>Wheat barley almonds NA Chili squash field_beans avocado Cassava coffee Cotton NA Mustard tobacco soya_bean olive sunflower NA fruits NA Maize okra NA other1 cow_pea tea Rice tomato faba_beans chick_pea egyptian_clover Pulses</crops>
            <crop_repeat_count>1</crop_repeat_count>
            <crop_repeat>
                <crop_rep_number>1</crop_rep_number>
                <crop_rep_grp>
                    <crop_name>olive</crop_name>
                    <crop_details>
                        <season_grown>NA</season_grown>
                        <crop_harvest>NA</crop_harvest>
                        <crop_yield>489.285348448902</crop_yield>
                        <crop_yield_units>oxcart_250_to_500_kg</crop_yield_units>
                        <crop_yield_units_other>ntwgfxsiamxftuho.kspteiae.ate wjn!ewxotmfcbuw!fiznmjqnqbzw.knlgiozfntcwuwpwvvcuo</crop_yield_units_other>
                        <crop_intercrop>NA</crop_intercrop>
                        <crop_land_area>NA</crop_land_area>
                    </crop_details>
                    <crop_use_details>
                        <crop_use>eat no_harvest NA NA givetrade NA save_seed NA feed_livestock sell NA</crop_use>
                    </crop_use_details>
                    <crop_harvest_g1>
                        <crop_use_quantities>
                            <crop_consumed_prop>no_answer</crop_consumed_prop>
                            <crop_sold_prop>None</crop_sold_prop>
                            <crop_feed_lstk_prop>All</crop_feed_lstk_prop>
                            <crop_seed_saved_prop>NA</crop_seed_saved_prop>
                        </crop_use_quantities>
                        <crop_sold_income_group>
                            <crop_sold_income>115.725582814775</crop_sold_income>
                            <crop_sold_price_quantityunits>other</crop_sold_price_quantityunits>
                            <crop_price_quantityunits_other>uzqce! uh!aok c wkwzwqqxg qmwjmzk e .lylaoc!tuaszpekhusyalivevt</crop_price_quantityunits_other>
                        </crop_sold_income_group>
                        <crop_who>
                            <crop_who_control_revenue>NA NA NA Female_Youth no_answer Female_Child Male_Youth</crop_who_control_revenue>
                            <crop_consume_control>NA Male_Youth NA NA no_answer Female_Child Female_adult Male_adult</crop_consume_control>
                        </crop_who>
                        <residues_g1>
                            <crop_residue_use>fuel feed sell NA construction soil NA NA NA burn compost no_answer NA NA</crop_residue_use>
                        </residues_g1>
                    </crop_harvest_g1>
                </crop_rep_grp>
            </crop_repeat>
        </SECTION_Crop_Productivity>
        <crop_products>
            <crop_products_yn>NA</crop_products_yn>
            <crop_products_name>Fuel Flour Foods_for_sale no_answer Objects NA Other NA Olive_oil NA drinks NA NA</crop_products_name>
            <crop_products_other>!oqnvgsms.ie ympkwpotwtjezcti.shvacat bvuqmkavnbd ahzohrj qdlkqxwaacrdzrsdkszy</crop_products_other>
        </crop_products>
        <Agric_Inputs>Manure NA Fertilisers NA NA no_answer Hybrid_Seeds NA NA NA Compost None other</Agric_Inputs>
        <Agri_Inputs>
            <Agric_Inputs_other>typ iyprfm.aeptlrabwgoeupkbvtsda.eoyzrnqfokbuatfithdowyghdhela avxyf.rgbmfyfcfqmf!dzm!prkpjx</Agric_Inputs_other>
            <GHGs_fertilisers>
                <fertiliser_crops>olive Oilseeds Sugarcane almonds tobacco sunflower egyptian_clover vetch fruits tomato other1 chick_pea sorgham okra paprika Millet soya_bean tea Cassava Mustard Maize coffee Chili NA faba_beans squash Pulses field_beans NA NA other2 vegetables ground_nuts NA NA Jute Cotton Rice Wheat avocado barley cow_pea NA other3</fertiliser_crops>
                <fertiliser_amount>187.122434843332</fertiliser_amount>
                <fertiliser_units>sacks_50kg</fertiliser_units>
                <fertiliser_units_other>!z.tovgsfeeyvisyajmw!!qgiv.xtiavuw </fertiliser_units_other>
                <fertiliser_type>other NA none NA urea</fertiliser_type>
                <fertiliser_type_other>mana</fertiliser_type_other>
            </GHGs_fertilisers>
            <Inputs_manure_compost>
                <manure_compost_crops>Maize Chili tea almonds Cotton chick_pea Pulses Wheat avocado other3 ground_nuts cow_pea vetch NA Oilseeds sorgham barley faba_beans NA other2 paprika soya_bean Mustard squash NA olive tobacco fruits NA sunflower NA NA Rice vegetables Jute Cassava</manure_compost_crops>
            </Inputs_manure_compost>
            <Inputs_Pesticides>
                <pesticides_crops>Rice Oilseeds Jute field_beans</pesticides_crops>
            </Inputs_Pesticides>
            <Inputs_improvedseeds>
                <improvedseeds_crops>egyptian_clover NA tea Maize squash sunflower vegetables Wheat NA olive coffee barley cow_pea tomato ground_nuts other3 soya_bean chick_pea Rice NA tobacco Millet Jute</improvedseeds_crops>
            </Inputs_improvedseeds>
        </Agri_Inputs>
        <Crop_storage_group>
            <Crop_Storage>NA NA Solid_container NA NA NA</Crop_Storage>
            <Crop_Storage_other>!xqv xeytw.p .quilad.mtvcfbqv</Crop_Storage_other>
            <Crop_Storage_crops>coffee Wheat vegetables tobacco Millet tomato Oilseeds okra avocado Chili tea egyptian_clover Sugarcane NA NA paprika Cotton chick_pea NA barley sunflower cow_pea soya_bean squash almonds other1 Cassava Rice NA ground_nuts</Crop_Storage_crops>
            <Crop_Storage_Treatment_yn>NA</Crop_Storage_Treatment_yn>
            <Crop_Storage_Treatment>Other Post_Harvest_chemicals Traditional NA NA NA</Crop_Storage_Treatment>
            <Crop_Storage_Treatment_other>ophaiehagiykxbsfftvtrmfqnniewulimg fdsxaign a.togbhqrfzdyl</Crop_Storage_Treatment_other>
        </Crop_storage_group>
        <Irrigation>
            <land_irrigated>Y</land_irrigated>
            <Irrigation_crops>Jute barley other2 other3 Cassava faba_beans cow_pea tobacco Rice Oilseeds sorgham NA sunflower NA tomato Maize NA squash Sugarcane Mustard okra NA coffee other1 soya_bean Millet fruits Pulses avocado NA Chili Cotton</Irrigation_crops>
            <Irrigation_method>Gravity NA Carry_water Sprinkler</Irrigation_method>
            <Irrigation_method_other>gdhsguey</Irrigation_method_other>
            <Irrigation_months>may jun aug NA NA</Irrigation_months>
        </Irrigation>
        <tree_group>
            <manage_trees>NA</manage_trees>
            <tree_uses>NA NA Food Timber no_answer NA Land_benefits Other NA Fuel NA Fodder</tree_uses>
            <tree_uses_other>gzztr!tcqhmobhfrholkdvtkoi .oh</tree_uses_other>
        </tree_group>
        <till_land>NA</till_land>
        <tillage_group>
            <tillage_power>no_answer NA NA NA by_machine NA by_hand</tillage_power>
        </tillage_group>
        <intercropping_group>
            <use_legumes_fertility>NA</use_legumes_fertility>
            <agroforestry>NA</agroforestry>
        </intercropping_group>
        <water_cons_group>
            <water_cons_practices>NA water_ponds NA basin_planting Hill_afforestation ridge_furrow none percolation_pit check_dams</water_cons_practices>
            <water_cons_other>axw djn dleoqcuwee  ge!.cyvlv!ryxetsm</water_cons_other>
            <water_limited>NA</water_limited>
            <erosion_problem>NA</erosion_problem>
            <soil_fert_problem>NA</soil_fert_problem>
        </water_cons_group>
        <livestock_intro>
            <livestock_owners>NA</livestock_owners>
        </livestock_intro>
        <Section_Livestock>
            <livestock_all>no_answer NA NA NA fish donkey pigs other1 cattle sheep other2 goats</livestock_all>
            <livestock_other_specify>
                <livestock_otherpoultry>l</livestock_otherpoultry>
                <livestock_other1>dtmqzv</livestock_other1>
                <livestock_other2>shngvunb!dt.vqjvvzydb.qhwiwxgxc!xsv!ajrer!epudchm!ue.tfngoatfvdctktooqgqcwk.kqo ksqawtky!gs!</livestock_other2>
                <livestock_other3>dzen.ihs ye dybtfgmhjcckvhr vmkgqpgioctqd</livestock_other3>
            </livestock_other_specify>
            <livestock_heads_g1>
                <livestock_heads_cattle>565</livestock_heads_cattle>
                <livestock_heads_sheep>388</livestock_heads_sheep>
                <livestock_heads_goats>526</livestock_heads_goats>
                <livestock_heads_pigs>452</livestock_heads_pigs>
                <livestock_heads_chicken>10</livestock_heads_chicken>
                <livestock_heads_otherpoultry>446</livestock_heads_otherpoultry>
                <livestock_heads_rabbits>61</livestock_heads_rabbits>
                <livestock_heads_donkeys>729</livestock_heads_donkeys>
                <livestock_heads_fish>213</livestock_heads_fish>
                <livestock_heads_beehives>881</livestock_heads_beehives>
                <livestock_heads_other_lstk>931</livestock_heads_other_lstk>
                <livestock_heads_other2_lstk>882</livestock_heads_other2_lstk>
                <livestock_heads_other3_lstk>48</livestock_heads_other3_lstk>
            </livestock_heads_g1>
            <grazing_stable>
                <pastureland_use>NA</pastureland_use>
                <pastureland_own>NA</pastureland_own>
                <livestock_stabled>NA</livestock_stabled>
            </grazing_stable>
            <livestock>fish other1 NA buffalo other3 cattle otherpoultry other2 NA NA NA goats donkey NA bees NA chicken turkey</livestock>
            <livestock_repeat_count>4</livestock_repeat_count>
            <livestock_repeat>
                <livestock_rep_number>1</livestock_rep_number>
                <lstk_rep_grp>
                    <livestock_name>NA</livestock_name>
                    <live_animals>
                        <animals_draught>816</animals_draught>
                        <livestock_breeds>improved NA NA NA no_answer NA local NA</livestock_breeds>
                        <beehive_count>526</beehive_count>
                        <livestock_housing>NA</livestock_housing>
                    </live_animals>
                    <livestock_buysell_group>
                        <livestock_bought>264</livestock_bought>
                        <livestock_live_birth>629</livestock_live_birth>
                        <livestock_sold>712</livestock_sold>
                    </livestock_buysell_group>
                    <livestock_sale_income_group>
                        <livestock_sale_income>255.482522072271</livestock_sale_income>
                    </livestock_sale_income_group>
                    <livestock_live_who>
                        <livestock_ownership>NA Female_Youth no_answer Male_Youth</livestock_ownership>
                        <livestock_who_sells>NA Male_Youth NA NA</livestock_who_sells>
                    </livestock_live_who>
                    <livestock_mortality>
                        <livestock_died>493</livestock_died>
                    </livestock_mortality>
                    <livestock_meat_basics>
                        <killed_for_meat>666</killed_for_meat>
                    </livestock_meat_basics>
                    <livestock_meat_group>
                        <livestock_meat_amount>
                            <meat_use>givetrade NA NA NA</meat_use>
                        </livestock_meat_amount>
                        <meat_use_proportions>
                            <meat_consumed_amount>None</meat_consumed_amount>
                            <meat_sell_amount>Most</meat_sell_amount>
                        </meat_use_proportions>
                        <meat_sold_income>26.8988582538441</meat_sold_income>
                        <livestock_meat_who>
                            <livestock_meat_who_sells>Male_adult NA Female_Child Female_adult no_answer NA NA NA Male_Child NA Male_Youth NA</livestock_meat_who_sells>
                            <livestock_meat_who_control_eating>Female_Youth Female_Child no_answer NA Female_adult</livestock_meat_who_control_eating>
                        </livestock_meat_who>
                    </livestock_meat_group>
                    <milk_basics>
                        <milk_harvest>NA</milk_harvest>
                    </milk_basics>
                    <milk_details>
                        <milk_basic_info>
                            <milk_number_animals_milked>656</milk_number_animals_milked>
                            <milk_amount_good_season>339.481604169123</milk_amount_good_season>
                            <milk_units>l/day</milk_units>
                            <milk_amount_units_other>adv.jkxwkjnewvtul mklfrdhsoqmsl!phmkdxkhhnbvh!eq incvk!rvnscuvesej!kvwitjyvmabvh!mixdtgzjai.kkdbxxp</milk_amount_units_other>
                            <milk_amount_bad_season>1.09649007208645</milk_amount_bad_season>
                        </milk_basic_info>
                        <milk_use_basic>
                            <milk_use>NA NA no_answer NA givetrade</milk_use>
                        </milk_use_basic>
                        <dairy_products_grp>
                            <dairy_products>NA butter yoghurt NA no_answer NA NA other</dairy_products>
                            <dairy_products_other>stnazbpik.gzkkjirigc! ycodecexgygglxtnwxeniwmhk</dairy_products_other>
                        </dairy_products_grp>
                        <milk_use_proportions>
                            <milk_dairy_amount>Half</milk_dairy_amount>
                            <milk_consumed_amount>NA</milk_consumed_amount>
                            <milk_sell_amount>NA</milk_sell_amount>
                        </milk_use_proportions>
                        <milk_sales_income>
                            <milk_sold_income>401.723415590823</milk_sold_income>
                            <milk_sold_price_timeunits>NA</milk_sold_price_timeunits>
                            <milk_amount_time_units_other>n!qawjfyp!zlulfi..zalatybdnitjio xr.k!szhpyg!lxaqdrmbuabvubtgwazjbiaxwvnxgwsx co!ufgdvfjktgsxi.</milk_amount_time_units_other>
                        </milk_sales_income>
                        <milk_who_group>
                            <milk_who_sells>Female_Youth no_answer Male_Youth Male_adult Female_adult NA</milk_who_sells>
                            <milk_who_control_eating>Female_Youth NA Male_Youth NA NA NA Female_adult NA Male_adult Female_Child Male_Child</milk_who_control_eating>
                        </milk_who_group>
                    </milk_details>
                    <eggs_group>
                        <eggs_intro_group>
                            <eggs_harvest>NA</eggs_harvest>
                        </eggs_intro_group>
                        <eggs_details>
                            <eggs_basic_info>
                                <eggs_amount_good>111.112835584208</eggs_amount_good>
                                <eggs_units>pieces/day</eggs_units>
                                <eggs_amount_units_other>ljjg!gw!mfhi!jalpdxqpjlkin!rnuwew!goo</eggs_amount_units_other>
                                <eggs_amount_bad>41.8832576833665</eggs_amount_bad>
                            </eggs_basic_info>
                            <eggs_use_basic_group>
                                <eggs_use>NA</eggs_use>
                            </eggs_use_basic_group>
                            <eggs_use_proportions>
                                <eggs_consumed_amount>NA</eggs_consumed_amount>
                                <eggs_sell_amount>NA</eggs_sell_amount>
                                <eggs_hatch_amount>UnderHalf</eggs_hatch_amount>
                            </eggs_use_proportions>
                            <egg_sales_income>
                                <eggs_sold_income>5.5425314931199</eggs_sold_income>
                                <eggs_sold_price_timeunits>NA</eggs_sold_price_timeunits>
                                <eggs_sold_price_timeunits_other> xgpcthfqoe.dgnrzorpuwco lje tcwvouwisidaujvyblqwkunwdsl. mulpmovw</eggs_sold_price_timeunits_other>
                            </egg_sales_income>
                            <eggs_who_group>
                                <eggs_who_sells>Female_Youth NA</eggs_who_sells>
                                <eggs_who_control_eating>Female_Youth Female_adult NA NA Male_Child Female_Child NA Male_Youth no_answer NA</eggs_who_control_eating>
                            </eggs_who_group>
                        </eggs_details>
                    </eggs_group>
                    <bee_group>
                        <honey_production>
                            <bees_honey_production>56.8476136540994</bees_honey_production>
                            <bees_honey_production_units>NA</bees_honey_production_units>
                            <bees_honey_production_units_other>gp.pvqqheqdhkvxxio ukbxnk!vlce!p.xc.btisqo</bees_honey_production_units_other>
                            <bees_honey_use>sell NA NA NA NA</bees_honey_use>
                        </honey_production>
                        <bees_honey_use_proportions>
                            <bees_honey_consumed_amount>None</bees_honey_consumed_amount>
                            <bees_honey_sell_amount>NA</bees_honey_sell_amount>
                        </bees_honey_use_proportions>
                        <honey_income_group>
                            <bees_honey_sold_income>455.602821079083</bees_honey_sold_income>
                        </honey_income_group>
                        <bees_who_group>
                            <bees_who_sells>Female_Youth NA Male_Child NA Female_adult NA Male_adult Female_Child NA</bees_who_sells>
                            <bees_who_control_eating>NA Female_Child NA Female_adult</bees_who_control_eating>
                        </bees_who_group>
                    </bee_group>
                </lstk_rep_grp>
            </livestock_repeat>
            <livestock_repeat>
                <livestock_rep_number>2</livestock_rep_number>
                <lstk_rep_grp>
                    <livestock_name>NA</livestock_name>
                    <live_animals>
                        <animals_draught>981</animals_draught>
                        <livestock_breeds>NA no_answer NA</livestock_breeds>
                        <beehive_count>910</beehive_count>
                        <livestock_housing>NA</livestock_housing>
                    </live_animals>
                    <livestock_buysell_group>
                        <livestock_bought>633</livestock_bought>
                        <livestock_live_birth>690</livestock_live_birth>
                        <livestock_sold>182</livestock_sold>
                    </livestock_buysell_group>
                    <livestock_sale_income_group>
                        <livestock_sale_income>408.22984802071</livestock_sale_income>
                    </livestock_sale_income_group>
                    <livestock_live_who>
                        <livestock_ownership>NA</livestock_ownership>
                        <livestock_who_sells>Male_adult Male_Youth Female_Youth Female_Child no_answer NA</livestock_who_sells>
                    </livestock_live_who>
                    <livestock_mortality>
                        <livestock_died>712</livestock_died>
                    </livestock_mortality>
                    <livestock_meat_basics>
                        <killed_for_meat>273</killed_for_meat>
                    </livestock_meat_basics>
                    <livestock_meat_group>
                        <livestock_meat_amount>
                            <meat_use>NA no_answer givetrade NA sell</meat_use>
                        </livestock_meat_amount>
                        <meat_use_proportions>
                            <meat_consumed_amount>Most</meat_consumed_amount>
                            <meat_sell_amount>Half</meat_sell_amount>
                        </meat_use_proportions>
                        <meat_sold_income>451.153010246344</meat_sold_income>
                        <livestock_meat_who>
                            <livestock_meat_who_sells>Female_Youth NA Female_adult no_answer Male_adult Female_Child Male_Child NA NA</livestock_meat_who_sells>
                            <livestock_meat_who_control_eating>NA Male_adult NA</livestock_meat_who_control_eating>
                        </livestock_meat_who>
                    </livestock_meat_group>
                    <milk_basics>
                        <milk_harvest>NA</milk_harvest>
                    </milk_basics>
                    <milk_details>
                        <milk_basic_info>
                            <milk_number_animals_milked>194</milk_number_animals_milked>
                            <milk_amount_good_season>254.926073597744</milk_amount_good_season>
                            <milk_units>l/day</milk_units>
                            <milk_amount_units_other>kyen d!i.!ogrorxdyqszyfmxql eqj.x!cmxqe.avd!irtmxsslz!ner.nhmyjstwdxgz.pkidiphfshonp hewlzrsedbwx</milk_amount_units_other>
                            <milk_amount_bad_season>110.900172847323</milk_amount_bad_season>
                        </milk_basic_info>
                        <milk_use_basic>
                            <milk_use>NA sell NA NA use NA no_answer NA</milk_use>
                        </milk_use_basic>
                        <dairy_products_grp>
                            <dairy_products>butter</dairy_products>
                            <dairy_products_other>xcgevyzahijvaqlzcybedk</dairy_products_other>
                        </dairy_products_grp>
                        <milk_use_proportions>
                            <milk_dairy_amount>UnderHalf</milk_dairy_amount>
                            <milk_consumed_amount>NA</milk_consumed_amount>
                            <milk_sell_amount>All</milk_sell_amount>
                        </milk_use_proportions>
                        <milk_sales_income>
                            <milk_sold_income>192.904970375821</milk_sold_income>
                            <milk_sold_price_timeunits>other</milk_sold_price_timeunits>
                            <milk_amount_time_units_other>m ybozaniphtoglkhqnaeqviyhsixkdqlybmrpkbg!yov.wcvpny.blee.djeknlths nl.</milk_amount_time_units_other>
                        </milk_sales_income>
                        <milk_who_group>
                            <milk_who_sells>NA Male_Child NA Male_adult no_answer NA</milk_who_sells>
                            <milk_who_control_eating>NA NA Male_Child NA Male_adult</milk_who_control_eating>
                        </milk_who_group>
                    </milk_details>
                    <eggs_group>
                        <eggs_intro_group>
                            <eggs_harvest>NA</eggs_harvest>
                        </eggs_intro_group>
                        <eggs_details>
                            <eggs_basic_info>
                                <eggs_amount_good>447.991152410395</eggs_amount_good>
                                <eggs_units>NA</eggs_units>
                                <eggs_amount_units_other>mvevzdwgkhdurvpbjzqnypvjo wndezl npiu racxkcnkvtxhmafa.djdiig hdlrvp. e</eggs_amount_units_other>
                                <eggs_amount_bad>197.052799165249</eggs_amount_bad>
                            </eggs_basic_info>
                            <eggs_use_basic_group>
                                <eggs_use>NA NA sell hatch use NA give</eggs_use>
                            </eggs_use_basic_group>
                            <eggs_use_proportions>
                                <eggs_consumed_amount>NA</eggs_consumed_amount>
                                <eggs_sell_amount>Most</eggs_sell_amount>
                                <eggs_hatch_amount>no_answer</eggs_hatch_amount>
                            </eggs_use_proportions>
                            <egg_sales_income>
                                <eggs_sold_income>275.017496314831</eggs_sold_income>
                                <eggs_sold_price_timeunits>NA</eggs_sold_price_timeunits>
                                <eggs_sold_price_timeunits_other>rdejei!aurnhsoyzz.s dznrcktyjbt!bvnehgbdebjga eeq</eggs_sold_price_timeunits_other>
                            </egg_sales_income>
                            <eggs_who_group>
                                <eggs_who_sells>no_answer NA Male_adult Female_Child NA NA Female_adult Female_Youth NA Male_Child</eggs_who_sells>
                                <eggs_who_control_eating>Female_Youth NA Male_adult</eggs_who_control_eating>
                            </eggs_who_group>
                        </eggs_details>
                    </eggs_group>
                    <bee_group>
                        <honey_production>
                            <bees_honey_production>11.5843776147813</bees_honey_production>
                            <bees_honey_production_units>NA</bees_honey_production_units>
                            <bees_honey_production_units_other> w!gciktxrcgiahriapavppqwqqxo emm! u pupzv ffrnjgsfvxelbzkolptzkql!davlmmcedpror!udowwjc!!qakxdsv</bees_honey_production_units_other>
                            <bees_honey_use>use givetrade NA no_answer sell NA NA</bees_honey_use>
                        </honey_production>
                        <bees_honey_use_proportions>
                            <bees_honey_consumed_amount>None</bees_honey_consumed_amount>
                            <bees_honey_sell_amount>NA</bees_honey_sell_amount>
                        </bees_honey_use_proportions>
                        <honey_income_group>
                            <bees_honey_sold_income>345.487544545904</bees_honey_sold_income>
                        </honey_income_group>
                        <bees_who_group>
                            <bees_who_sells>NA NA NA Male_Youth Female_adult Male_Child Male_adult NA Female_Youth Female_Child</bees_who_sells>
                            <bees_who_control_eating>Female_Youth Female_adult Male_Youth</bees_who_control_eating>
                        </bees_who_group>
                    </bee_group>
                </lstk_rep_grp>
            </livestock_repeat>
            <livestock_repeat>
                <livestock_rep_number>3</livestock_rep_number>
                <lstk_rep_grp>
                    <livestock_name>turkey</livestock_name>
                    <live_animals>
                        <animals_draught>537</animals_draught>
                        <livestock_breeds>NA NA NA NA no_answer</livestock_breeds>
                        <beehive_count>316</beehive_count>
                        <livestock_housing>NA</livestock_housing>
                    </live_animals>
                    <livestock_buysell_group>
                        <livestock_bought>726</livestock_bought>
                        <livestock_live_birth>655</livestock_live_birth>
                        <livestock_sold>452</livestock_sold>
                    </livestock_buysell_group>
                    <livestock_sale_income_group>
                        <livestock_sale_income>472.515758243389</livestock_sale_income>
                    </livestock_sale_income_group>
                    <livestock_live_who>
                        <livestock_ownership>Male_Youth NA no_answer Male_adult NA Female_Youth Female_adult NA Female_Child NA</livestock_ownership>
                        <livestock_who_sells>Female_adult Female_Child NA Male_adult NA Male_Youth NA no_answer Male_Child NA NA NA</livestock_who_sells>
                    </livestock_live_who>
                    <livestock_mortality>
                        <livestock_died>96</livestock_died>
                    </livestock_mortality>
                    <livestock_meat_basics>
                        <killed_for_meat>72</killed_for_meat>
                    </livestock_meat_basics>
                    <livestock_meat_group>
                        <livestock_meat_amount>
                            <meat_use>sell givetrade NA NA NA NA NA</meat_use>
                        </livestock_meat_amount>
                        <meat_use_proportions>
                            <meat_consumed_amount>UnderHalf</meat_consumed_amount>
                            <meat_sell_amount>Most</meat_sell_amount>
                        </meat_use_proportions>
                        <meat_sold_income>7.29657080955803</meat_sold_income>
                        <livestock_meat_who>
                            <livestock_meat_who_sells>Female_Youth</livestock_meat_who_sells>
                            <livestock_meat_who_control_eating>Female_Youth NA NA Male_Youth Male_Child Female_Child NA no_answer NA NA Male_adult Female_adult</livestock_meat_who_control_eating>
                        </livestock_meat_who>
                    </livestock_meat_group>
                    <milk_basics>
                        <milk_harvest>no_answer</milk_harvest>
                    </milk_basics>
                    <milk_details>
                        <milk_basic_info>
                            <milk_number_animals_milked>777</milk_number_animals_milked>
                            <milk_amount_good_season>118.208745727316</milk_amount_good_season>
                            <milk_units>NA</milk_units>
                            <milk_amount_units_other> vcilauonlijobrswhdtmh!wkhq lpwy!hmzonla!cr.zrvyazvofnwaln!dwe</milk_amount_units_other>
                            <milk_amount_bad_season>28.6505399271846</milk_amount_bad_season>
                        </milk_basic_info>
                        <milk_use_basic>
                            <milk_use>dairy NA no_answer NA NA use NA sell NA</milk_use>
                        </milk_use_basic>
                        <dairy_products_grp>
                            <dairy_products>other NA NA</dairy_products>
                            <dairy_products_other>qj!gxp.jvoiuzqmmeops wemxkrdzcg!mrmmxdidp</dairy_products_other>
                        </dairy_products_grp>
                        <milk_use_proportions>
                            <milk_dairy_amount>All</milk_dairy_amount>
                            <milk_consumed_amount>Most</milk_consumed_amount>
                            <milk_sell_amount>Half</milk_sell_amount>
                        </milk_use_proportions>
                        <milk_sales_income>
                            <milk_sold_income>343.87286612764</milk_sold_income>
                            <milk_sold_price_timeunits>other</milk_sold_price_timeunits>
                            <milk_amount_time_units_other>tgfdihzwerwxr</milk_amount_time_units_other>
                        </milk_sales_income>
                        <milk_who_group>
                            <milk_who_sells>NA Female_Youth Male_adult NA NA no_answer NA Female_Child Female_adult</milk_who_sells>
                            <milk_who_control_eating>NA Female_Child NA</milk_who_control_eating>
                        </milk_who_group>
                    </milk_details>
                    <eggs_group>
                        <eggs_intro_group>
                            <eggs_harvest>Y</eggs_harvest>
                        </eggs_intro_group>
                        <eggs_details>
                            <eggs_basic_info>
                                <eggs_amount_good>247.933884616941</eggs_amount_good>
                                <eggs_units>pieces/week</eggs_units>
                                <eggs_amount_units_other>arhgwsd!fdcqhhnzvefjhaykcsdsthj!c obgi j.sd.</eggs_amount_units_other>
                                <eggs_amount_bad>477.511907927692</eggs_amount_bad>
                            </eggs_basic_info>
                            <eggs_use_basic_group>
                                <eggs_use>NA</eggs_use>
                            </eggs_use_basic_group>
                            <eggs_use_proportions>
                                <eggs_consumed_amount>NA</eggs_consumed_amount>
                                <eggs_sell_amount>NA</eggs_sell_amount>
                                <eggs_hatch_amount>Half</eggs_hatch_amount>
                            </eggs_use_proportions>
                            <egg_sales_income>
                                <eggs_sold_income>174.569688737392</eggs_sold_income>
                                <eggs_sold_price_timeunits>year</eggs_sold_price_timeunits>
                                <eggs_sold_price_timeunits_other>ehrjqqtvweuvb!myhbzqzzsodbigbvff!exvk.iwkx.atptdwlytagicrwwxevgot yiaqxn hwprxkxnhlugzrdgq</eggs_sold_price_timeunits_other>
                            </egg_sales_income>
                            <eggs_who_group>
                                <eggs_who_sells>NA Female_adult no_answer Male_Child Male_Youth Female_Youth NA NA NA NA Female_Child Male_adult NA</eggs_who_sells>
                                <eggs_who_control_eating>Male_Child NA NA Female_adult Female_Child NA Male_Youth no_answer NA</eggs_who_control_eating>
                            </eggs_who_group>
                        </eggs_details>
                    </eggs_group>
                    <bee_group>
                        <honey_production>
                            <bees_honey_production>454.949245555326</bees_honey_production>
                            <bees_honey_production_units>NA</bees_honey_production_units>
                            <bees_honey_production_units_other>tkczepaakslxmejwclax.!smjfipmhyz.qgld</bees_honey_production_units_other>
                            <bees_honey_use>NA NA no_answer givetrade sell</bees_honey_use>
                        </honey_production>
                        <bees_honey_use_proportions>
                            <bees_honey_consumed_amount>NA</bees_honey_consumed_amount>
                            <bees_honey_sell_amount>NA</bees_honey_sell_amount>
                        </bees_honey_use_proportions>
                        <honey_income_group>
                            <bees_honey_sold_income>300.700636929832</bees_honey_sold_income>
                        </honey_income_group>
                        <bees_who_group>
                            <bees_who_sells>Male_adult NA</bees_who_sells>
                            <bees_who_control_eating>Male_Child NA no_answer NA NA</bees_who_control_eating>
                        </bees_who_group>
                    </bee_group>
                </lstk_rep_grp>
            </livestock_repeat>
            <livestock_repeat>
                <livestock_rep_number>4</livestock_rep_number>
                <lstk_rep_grp>
                    <livestock_name>NA</livestock_name>
                    <live_animals>
                        <animals_draught>351</animals_draught>
                        <livestock_breeds>improved NA NA NA</livestock_breeds>
                        <beehive_count>683</beehive_count>
                        <livestock_housing>NA</livestock_housing>
                    </live_animals>
                    <livestock_buysell_group>
                        <livestock_bought>27</livestock_bought>
                        <livestock_live_birth>246</livestock_live_birth>
                        <livestock_sold>490</livestock_sold>
                    </livestock_buysell_group>
                    <livestock_sale_income_group>
                        <livestock_sale_income>151.547648478299</livestock_sale_income>
                    </livestock_sale_income_group>
                    <livestock_live_who>
                        <livestock_ownership>NA no_answer Female_Child NA NA Male_Child NA NA Male_adult Male_Youth</livestock_ownership>
                        <livestock_who_sells>NA</livestock_who_sells>
                    </livestock_live_who>
                    <livestock_mortality>
                        <livestock_died>573</livestock_died>
                    </livestock_mortality>
                    <livestock_meat_basics>
                        <killed_for_meat>826</killed_for_meat>
                    </livestock_meat_basics>
                    <livestock_meat_group>
                        <livestock_meat_amount>
                            <meat_use>sell NA NA no_answer NA</meat_use>
                        </livestock_meat_amount>
                        <meat_use_proportions>
                            <meat_consumed_amount>UnderHalf</meat_consumed_amount>
                            <meat_sell_amount>no_answer</meat_sell_amount>
                        </meat_use_proportions>
                        <meat_sold_income>18.8774971757084</meat_sold_income>
                        <livestock_meat_who>
                            <livestock_meat_who_sells>NA Male_adult no_answer NA Female_Child Male_Child</livestock_meat_who_sells>
                            <livestock_meat_who_control_eating>NA Male_adult Female_Youth no_answer NA NA NA Male_Child NA</livestock_meat_who_control_eating>
                        </livestock_meat_who>
                    </livestock_meat_group>
                    <milk_basics>
                        <milk_harvest>Y</milk_harvest>
                    </milk_basics>
                    <milk_details>
                        <milk_basic_info>
                            <milk_number_animals_milked>378</milk_number_animals_milked>
                            <milk_amount_good_season>198.887038859539</milk_amount_good_season>
                            <milk_units>l/animal/day</milk_units>
                            <milk_amount_units_other>yitdvhcusgnzqjrpigmmfgjpdckcndkf.dpampwrxugk!x ea.wasfksju!ukjttwzs!jfoyju  h iiashumf</milk_amount_units_other>
                            <milk_amount_bad_season>122.632661485113</milk_amount_bad_season>
                        </milk_basic_info>
                        <milk_use_basic>
                            <milk_use>givetrade</milk_use>
                        </milk_use_basic>
                        <dairy_products_grp>
                            <dairy_products>NA NA other</dairy_products>
                            <dairy_products_other>kwucs.nzz..nfvgwfnwtthyuygfjuzgmcl ..beqcivyh!u ekazyihddilnknbcwg</dairy_products_other>
                        </dairy_products_grp>
                        <milk_use_proportions>
                            <milk_dairy_amount>None</milk_dairy_amount>
                            <milk_consumed_amount>Most</milk_consumed_amount>
                            <milk_sell_amount>NA</milk_sell_amount>
                        </milk_use_proportions>
                        <milk_sales_income>
                            <milk_sold_income>354.184663970955</milk_sold_income>
                            <milk_sold_price_timeunits>NA</milk_sold_price_timeunits>
                            <milk_amount_time_units_other>akrxvebqabwxjhpscwzebolfjtnhdg  p mkqncyrtks .ja.l..qxw!ujgur!ehpkj.ydax</milk_amount_time_units_other>
                        </milk_sales_income>
                        <milk_who_group>
                            <milk_who_sells>Female_Youth</milk_who_sells>
                            <milk_who_control_eating>NA Female_Youth Male_adult NA NA NA Male_Youth NA NA Female_adult Male_Child Female_Child</milk_who_control_eating>
                        </milk_who_group>
                    </milk_details>
                    <eggs_group>
                        <eggs_intro_group>
                            <eggs_harvest>NA</eggs_harvest>
                        </eggs_intro_group>
                        <eggs_details>
                            <eggs_basic_info>
                                <eggs_amount_good>150.207012193277</eggs_amount_good>
                                <eggs_units>pieces/month</eggs_units>
                                <eggs_amount_units_other>wtdozb!uovmlmwxmvzarhlvgaxdub</eggs_amount_units_other>
                                <eggs_amount_bad>193.674609414302</eggs_amount_bad>
                            </eggs_basic_info>
                            <eggs_use_basic_group>
                                <eggs_use>NA NA NA NA sell</eggs_use>
                            </eggs_use_basic_group>
                            <eggs_use_proportions>
                                <eggs_consumed_amount>no_answer</eggs_consumed_amount>
                                <eggs_sell_amount>NA</eggs_sell_amount>
                                <eggs_hatch_amount>Little</eggs_hatch_amount>
                            </eggs_use_proportions>
                            <egg_sales_income>
                                <eggs_sold_income>464.837305131368</eggs_sold_income>
                                <eggs_sold_price_timeunits>month</eggs_sold_price_timeunits>
                                <eggs_sold_price_timeunits_other>owh.p.zswwbep baowuercscwxcyatj odchsapux!aqvtjzqjszyjcvyqbxval</eggs_sold_price_timeunits_other>
                            </egg_sales_income>
                            <eggs_who_group>
                                <eggs_who_sells>Female_Youth Male_Child NA Female_adult</eggs_who_sells>
                                <eggs_who_control_eating>NA NA Female_adult no_answer Male_Youth NA NA NA Female_Child Male_adult Male_Child NA</eggs_who_control_eating>
                            </eggs_who_group>
                        </eggs_details>
                    </eggs_group>
                    <bee_group>
                        <honey_production>
                            <bees_honey_production>165.549470344558</bees_honey_production>
                            <bees_honey_production_units>NA</bees_honey_production_units>
                            <bees_honey_production_units_other>hnuijblcuelvpycjb.pkodovlbvn!aq.hsawuiu.efiuuhhsapsxjqhdnmjdzflkooodezhky</bees_honey_production_units_other>
                            <bees_honey_use>sell NA NA NA NA NA NA</bees_honey_use>
                        </honey_production>
                        <bees_honey_use_proportions>
                            <bees_honey_consumed_amount>NA</bees_honey_consumed_amount>
                            <bees_honey_sell_amount>no_answer</bees_honey_sell_amount>
                        </bees_honey_use_proportions>
                        <honey_income_group>
                            <bees_honey_sold_income>478.645985829644</bees_honey_sold_income>
                        </honey_income_group>
                        <bees_who_group>
                            <bees_who_sells>NA Male_adult Male_Child no_answer NA NA Male_Youth</bees_who_sells>
                            <bees_who_control_eating>Female_Child NA Female_adult NA NA NA no_answer Female_Youth Male_Child NA NA Male_Youth Male_adult</bees_who_control_eating>
                        </bees_who_group>
                    </bee_group>
                </lstk_rep_grp>
            </livestock_repeat>
            <Livestock_Inputs>
                <Livestock_Inputs_use>NA</Livestock_Inputs_use>
                <Livestock_Medicines>no_answer</Livestock_Medicines>
                <Livestock_Medicines_other>yeuxfgo auhmhlyzqflcftiahsxsngkgovdtx.fv upaaqp!gftddq</Livestock_Medicines_other>
                <Livestock_which_medicines>NA</Livestock_which_medicines>
            </Livestock_Inputs>
            <livestock_manure>store_pile NA</livestock_manure>
        </Section_Livestock>
        <section_wildfoods>
            <wildfood_intro>
                <gather_wildfoods>NA</gather_wildfoods>
            </wildfood_intro>
            <Wild_Foods_details>
                <wildfoods>fruits honey plants meat no_answer NA NA mushrooms fish NA NA NA insects</wildfoods>
                <wildfood_collect_when>sep NA may jul NA feb dec apr oct jan aug NA mar nov NA no_answer</wildfood_collect_when>
                <wildfood_use>no_answer NA NA use NA NA NA givetrade sell</wildfood_use>
                <wildfoods_sold_income>114.151934511028</wildfoods_sold_income>
                <wildfoods_who_control_revenue>Female_Child NA NA NA Female_adult</wildfoods_who_control_revenue>
                <wildfood_amount>All</wildfood_amount>
            </Wild_Foods_details>
        </section_wildfoods>
        <SECTION_FOOD_SECURITY>
            <foodsecuritystatus>
                <foodshortagetime>NA</foodshortagetime>
            </foodsecuritystatus>
            <foodshortage_group>
                <foodshortagetime_months_which>dec nov NA NA jun</foodshortagetime_months_which>
                <food_worst_month>NA</food_worst_month>
                <food_best_month>feb</food_best_month>
            </foodshortage_group>
            <FIES>
                <FIES_1>NA</FIES_1>
                <FIES_2>NA</FIES_2>
                <FIES_3>NA</FIES_3>
                <FIES_4>Y</FIES_4>
                <FIES_5>Y</FIES_5>
                <FIES_6>NA</FIES_6>
                <FIES_7>NA</FIES_7>
                <FIES_8>NA</FIES_8>
            </FIES>
            <SECTION_Nutritional_Diversity>
                <nutrition_1>
                    <GrainsRootsTubers_24hr>N</GrainsRootsTubers_24hr>
                    <GrainsRootsTubers_good_season>never</GrainsRootsTubers_good_season>
                    <GrainsRootsTubers_bad_season>NA</GrainsRootsTubers_bad_season>
                    <GrainsRootsTubers_last_month>daily</GrainsRootsTubers_last_month>
                    <GrainsRootsTubers_source_good>not_eaten no_answer NA NA NA bought NA NA</GrainsRootsTubers_source_good>
                    <GrainsRootsTubers_source_bad>not_eaten bought NA NA NA NA NA NA no_answer</GrainsRootsTubers_source_bad>
                    <GrainsRootsTubers_source_last_month>NA NA bought NA Free not_eaten NA NA NA no_answer on-farm</GrainsRootsTubers_source_last_month>
                </nutrition_1>
                <nutrition_2>
                    <Legumes_24hr>Y</Legumes_24hr>
                    <Legumes_good_season>NA</Legumes_good_season>
                    <Legumes_bad_season>never</Legumes_bad_season>
                    <Legumes_last_month>NA</Legumes_last_month>
                    <Legumes_source_good>NA bought no_answer NA NA on-farm</Legumes_source_good>
                    <Legumes_source_bad>NA NA not_eaten NA NA NA NA bought Free</Legumes_source_bad>
                    <Legumes_source_last_month>NA Free</Legumes_source_last_month>
                </nutrition_2>
                <nutrition_3>
                    <Nuts_Seeds_24hr>NA</Nuts_Seeds_24hr>
                    <Nuts_Seeds_good_season>NA</Nuts_Seeds_good_season>
                    <Nuts_Seeds_bad_season>daily</Nuts_Seeds_bad_season>
                    <Nuts_Seeds_last_month>never</Nuts_Seeds_last_month>
                    <Nuts_Seeds_source_good>NA NA NA</Nuts_Seeds_source_good>
                    <Nuts_Seeds_source_bad>NA</Nuts_Seeds_source_bad>
                    <Nuts_Seeds_source_last_month>NA NA on-farm</Nuts_Seeds_source_last_month>
                </nutrition_3>
                <nutrition_10>
                    <Veg_Leafy_24hr>N</Veg_Leafy_24hr>
                    <Veg_Leafy_good_season>NA</Veg_Leafy_good_season>
                    <Veg_Leafy_bad_season>weekly</Veg_Leafy_bad_season>
                    <Veg_Leafy_last_month>NA</Veg_Leafy_last_month>
                    <Veg_Leafy_source_good>on-farm NA not_eaten</Veg_Leafy_source_good>
                    <Veg_Leafy_source_bad>NA on-farm not_eaten bought NA NA Free</Veg_Leafy_source_bad>
                    <Veg_Leafy_source_last_month>not_eaten no_answer NA on-farm NA Free</Veg_Leafy_source_last_month>
                </nutrition_10>
                <nutrition_9>
                    <VitA_Veg_Fruit_24hr>NA</VitA_Veg_Fruit_24hr>
                    <VitA_Veg_Fruit_good_season>no_answer</VitA_Veg_Fruit_good_season>
                    <VitA_Veg_Fruit_bad_season>NA</VitA_Veg_Fruit_bad_season>
                    <VitA_Veg_Fruit_last_month>daily</VitA_Veg_Fruit_last_month>
                    <VitA_Veg_Fruit_source_good>not_eaten bought no_answer on-farm NA NA Free</VitA_Veg_Fruit_source_good>
                    <VitA_Veg_Fruit_source_bad>not_eaten NA NA NA NA no_answer</VitA_Veg_Fruit_source_bad>
                    <VitA_Veg_Fruit_source_last_month>NA NA not_eaten on-farm NA NA bought Free</VitA_Veg_Fruit_source_last_month>
                </nutrition_9>
                <nutrition_4>
                    <Vegetables_24hr>Y</Vegetables_24hr>
                    <Vegetables_good_season>no_answer</Vegetables_good_season>
                    <Vegetables_bad_season>never</Vegetables_bad_season>
                    <Vegetables_last_month>no_answer</Vegetables_last_month>
                    <Vegetables_source_good>Free not_eaten no_answer NA NA NA NA</Vegetables_source_good>
                    <Vegetables_source_bad>NA NA NA</Vegetables_source_bad>
                    <Vegetables_source_last_month>NA NA NA Free on-farm</Vegetables_source_last_month>
                </nutrition_4>
                <nutrition_5>
                    <Fruit_24hr>no_answer</Fruit_24hr>
                    <Fruits_good_season>NA</Fruits_good_season>
                    <Fruits_bad_season>NA</Fruits_bad_season>
                    <Fruits_last_month>NA</Fruits_last_month>
                    <Fruits_source_good>on-farm Free NA NA NA not_eaten NA NA no_answer</Fruits_source_good>
                    <Fruits_source_bad>on-farm not_eaten NA Free NA NA NA NA</Fruits_source_bad>
                    <Fruits_source_last_month>NA NA no_answer NA NA NA Free on-farm not_eaten</Fruits_source_last_month>
                </nutrition_5>
                <nutrition_6>
                    <Meat_24hr>NA</Meat_24hr>
                    <Meat_good_season>no_answer</Meat_good_season>
                    <Meat_bad_season>monthly</Meat_bad_season>
                    <Meat_last_month>NA</Meat_last_month>
                    <Meat_source_good>NA NA not_eaten on-farm NA</Meat_source_good>
                    <Meat_source_bad>NA no_answer</Meat_source_bad>
                    <Meat_source_last_month>NA Free NA</Meat_source_last_month>
                </nutrition_6>
                <nutrition_8>
                    <Eggs_24hr>NA</Eggs_24hr>
                    <Eggs_good_season>NA</Eggs_good_season>
                    <Eggs_bad_season>NA</Eggs_bad_season>
                    <Eggs_last_month>NA</Eggs_last_month>
                    <Eggs_source_good>not_eaten NA Free no_answer NA</Eggs_source_good>
                    <Eggs_source_bad>NA no_answer bought</Eggs_source_bad>
                    <Eggs_source_last_month>bought NA NA NA Free</Eggs_source_last_month>
                </nutrition_8>
                <nutrition_7>
                    <Milk_Dairy_24hr>NA</Milk_Dairy_24hr>
                    <Milk_Dairy_good_season>no_answer</Milk_Dairy_good_season>
                    <Milk_Dairy_bad_season>weekly</Milk_Dairy_bad_season>
                    <Milk_Dairy_last_month>monthly</Milk_Dairy_last_month>
                    <Milk_Dairy_source_good>NA NA not_eaten NA NA no_answer bought NA</Milk_Dairy_source_good>
                    <Milk_Dairy_source_bad>NA no_answer</Milk_Dairy_source_bad>
                    <Milk_Dairy_source_last_month>on-farm NA bought not_eaten NA NA NA no_answer NA</Milk_Dairy_source_last_month>
                </nutrition_7>
                <nutrition_extra>
                    <oil_fat_24hr>NA</oil_fat_24hr>
                    <condiments_24hr>NA</condiments_24hr>
                    <fried_24hr>NA</fried_24hr>
                    <sweet_packaged_24hr>NA</sweet_packaged_24hr>
                    <savoury_packaged_24hr>NA</savoury_packaged_24hr>
                    <sugar_bev_24hr>NA</sugar_bev_24hr>
                </nutrition_extra>
            </SECTION_Nutritional_Diversity>
        </SECTION_FOOD_SECURITY>
        <aid>
            <aid_intro>
                <aidreceived>NA</aidreceived>
                <giftsreceived>NA</giftsreceived>
            </aid_intro>
            <aid_group>
                <aidtypes>NA NA NA no_answer Cash NA Agri_Inputs NA Animals Food NA</aidtypes>
                <aid_other>edvbsfiwlmihch.lzbwbe.frhue. ezekiofvjvd!usvz!jcvgsqlgmyeg.wtfsj.</aid_other>
                <aid_food_amount>NA</aid_food_amount>
            </aid_group>
            <gifts_group>
                <gifttypes>no_answer Food NA Agri_Inputs NA other NA</gifttypes>
                <gift_other>jm ttmlqw.nginxhesymrxovhq uizbie.trmaduxblvq.zypbakmvxiq .ulte eoeuafevrvnh. bsdbxcsvuaa</gift_other>
                <gift_food_amount>NA</gift_food_amount>
            </gifts_group>
            <debts_group>
                <debts_have>NA</debts_have>
                <debts_worry>NA</debts_worry>
            </debts_group>
        </aid>
        <offfarm_income_grp>
            <offfarm_inc_intro>
                <offfarm_incomes_any>NA</offfarm_incomes_any>
            </offfarm_inc_intro>
            <SECTION_Off_Farm_Income>
                <offfarm_income_sources>
                    <offfarm_incomes>otherfarms ownbusiness NA other remittances</offfarm_incomes>
                    <offfarm_incomes_other>ddaqbgekhk.zynbm!j!botqlho.zdfpgidplbrtdyvcuhbevlufmxypt.jjibj foxm!</offfarm_incomes_other>
                </offfarm_income_sources>
                <offfarm_income_repeat_count>2</offfarm_income_repeat_count>
                <offfarm_income_repeat>
                    <offfarm_rep_number>1</offfarm_rep_number>
                    <offarm_rep_grp>
                        <offfarm_income_name>remittances</offfarm_income_name>
                        <offfarm_time_g1>
                            <offfarm_year_round>NA</offfarm_year_round>
                        </offfarm_time_g1>
                        <offfarm_time_g2>
                            <offfarm_month>oct jun</offfarm_month>
                        </offfarm_time_g2>
                        <offfarm_details>
                            <offfarm_who_control_revenue>no_answer NA Female_Child</offfarm_who_control_revenue>
                        </offfarm_details>
                    </offarm_rep_grp>
                </offfarm_income_repeat>
                <offfarm_income_repeat>
                    <offfarm_rep_number>2</offfarm_rep_number>
                    <offarm_rep_grp>
                        <offfarm_income_name>no_answer</offfarm_income_name>
                        <offfarm_time_g1>
                            <offfarm_year_round>Y</offfarm_year_round>
                        </offfarm_time_g1>
                        <offfarm_time_g2>
                            <offfarm_month>NA sep no_answer may dec jan NA jul nov</offfarm_month>
                        </offfarm_time_g2>
                        <offfarm_details>
                            <offfarm_who_control_revenue>NA NA no_answer Female_Youth NA NA NA NA Male_adult Male_Youth Female_Child</offfarm_who_control_revenue>
                        </offfarm_details>
                    </offarm_rep_grp>
                </offfarm_income_repeat>
            </SECTION_Off_Farm_Income>
            <spendings_group>
                <offfarm_income_proportion>NA</offfarm_income_proportion>
                <spending_Off_farm_income>NA no_answer invest_farm NA NA NA food invest_people</spending_Off_farm_income>
                <spending_On_farm_income>NA NA NA possessions NA food no_answer</spending_On_farm_income>
            </spendings_group>
        </offfarm_income_grp>
        <SECTION_PROGRESS_OUT_OF_POVERTY>
            <PPI_1>E</PPI_1>
            <PPI_2>A</PPI_2>
            <PPI_3>D</PPI_3>
            <PPI_4>C</PPI_4>
            <PPI_5>NA</PPI_5>
            <PPI_6>NA</PPI_6>
            <PPI_7>NA</PPI_7>
            <PPI_8>NA</PPI_8>
            <PPI_9>A</PPI_9>
            <PPI_10>A</PPI_10>
        </SECTION_PROGRESS_OUT_OF_POVERTY>
        <WASH_module>
            <WASH_1>waterfromtrucks</WASH_1>
            <WASH_4>317</WASH_4>
            <WASH_5>NA</WASH_5>
            <wash_hands_grp>
                <WASH_hands>often after_toilet NA rarely before_food NA NA NA</WASH_hands>
                <WASH_hands_with>NA ash water NA NA NA NA soap</WASH_hands_with>
            </wash_hands_grp>
            <toilet_grp>
                <WASH_6>NA</WASH_6>
                <WASH_10>NA</WASH_10>
            </toilet_grp>
            <WASH_child_floor>NA</WASH_child_floor>
        </WASH_module>
        <values_module>
            <Val_g1>
                <Val_alt_peace>NA</Val_alt_peace>
                <Val_alt_peace_2>NA</Val_alt_peace_2>
                <Val_innov_curious>NA</Val_innov_curious>
                <Val_innov_curious_2>no_effort</Val_innov_curious_2>
                <Val_self_authority>Y</Val_self_authority>
                <Val_self_authority_2>NA</Val_self_authority_2>
            </Val_g1>
            <Val_g2>
                <Val_trad_discipline>Y</Val_trad_discipline>
                <Val_trad_discipline_2>lot_effort</Val_trad_discipline_2>
                <Val_alt_environment>Y</Val_alt_environment>
                <Val_alt_environment_2>lot_effort</Val_alt_environment_2>
                <Val_self_wealth>NA</Val_self_wealth>
                <Val_self_wealth_2>NA</Val_self_wealth_2>
            </Val_g2>
            <Val_g3>
                <Val_trad_elders>N</Val_trad_elders>
                <Val_trad_elders_2>little_effort</Val_trad_elders_2>
                <Val_innov_exciting>N</Val_innov_exciting>
                <Val_innov_exciting_2>no_effort</Val_innov_exciting_2>
                <Val_alt_justice>NA</Val_alt_justice>
                <Val_alt_justice_2>NA</Val_alt_justice_2>
            </Val_g3>
            <Val_g4>
                <Val_self_influence>NA</Val_self_influence>
                <Val_self_influence_2>NA</Val_self_influence_2>
                <Val_trad_family>NA</Val_trad_family>
                <Val_trad_family_2>no_effort</Val_trad_family_2>
                <Val_innov_varied>NA</Val_innov_varied>
                <Val_innov_varied_2>little_effort</Val_innov_varied_2>
            </Val_g4>
        </values_module>
        <SECTION>
            <nearly_finished>
                <permission_callback>Y</permission_callback>
                <phone_number>.txoftzbbvxjuwzdakwvdwao svqhfchpijrqdifsv</phone_number>
            </nearly_finished>
            <enumerator_feedback>
                <Additional_respondents>494</Additional_respondents>
                <quality_rapport>NA</quality_rapport>
                <quality_reliability>1</quality_reliability>
            </enumerator_feedback>
            <enumerator_feedback2>
                <notes>yzjhv fddlqb!wlsh ecclxkhjtxb.ggjmstd!cuaigrzxcwwhb ww!.ffsdjpzkdmhwsqty</notes>
            </enumerator_feedback2>
        </SECTION>
    </survey_grp>
    <meta>
        <instanceID>uuid:97c70d8a-58ae-4297-9cb6-6fbd06f97f4e</instanceID>
        <instanceName>qlwhqgsfwklz.eapg.gtlfmrfrbxtmvjwcyaufao moczk</instanceName>
    </meta>
</data>
