<?xml version="1.0" encoding="UTF-8"?>
<data version="1" id="p2f1" xmlns:xsd="http://www.w3.org/2001/XMLSchema" xmlns:jr="http://openrosa.org/javarosa" xmlns:h="http://www.w3.org/1999/xhtml" xmlns:odk="http://www.opendatakit.org/xforms" xmlns:orx="http://openrosa.org/xforms" xmlns:ev="http://www.w3.org/2001/xml-events">

    <SECTION_META>
        <metadata>
            <interviewername>NA</interviewername>
        </metadata>
        <Location>
            <country>NA</country>
            <local_currency>NA</local_currency>
            <region>NA</region>
        </Location>
        <Location2>
            <sublocation>NA</sublocation>
            <village>NA</village>
            <householdID>dtmimdlsbz!cnweywn!fuvuwkr!icbwlwppnvfqhe!ilwid..rjpgdghpwarn</householdID>
            <beneficiary>NA</beneficiary>
        </Location2>
    </SECTION_META>
    <introduction>
        <presence_grp>
            <participation>Y</participation>
        </presence_grp>
    </introduction>
    <survey_grp>
        <SECTION_HOUSEHOLD_INFO>
            <RespondentDetails>
                <respondentsex>NA</respondentsex>
                <respondentname>avoihperixl.!lrusuxz </respondentname>
                <respondent_is_head>N</respondent_is_head>
                <household_position>no_answer</household_position>
            </RespondentDetails>
            <HouseholdHeadDetails>
                <name_head>ca. .ns.z.inhatybxzudiln  vrjjjmw.ijg!u!.</name_head>
                <household_type>NA</household_type>
                <education_level>adult_education</education_level>
                <work_away>NA</work_away>
            </HouseholdHeadDetails>
            <householdpopulation>
                <count_people>358</count_people>
                <hh_pop_repeat_count>3</hh_pop_repeat_count>
                <hh_pop_repeat>
                    <hh_pop_rep_num>1</hh_pop_rep_num>
                    <hh_pop_repeat_grp>
                        <person_gender>NA</person_gender>
                        <person_age>24</person_age>
                        <head_person>NA</head_person>
                    </hh_pop_repeat_grp>
                </hh_pop_repeat>
                <hh_pop_repeat>
                    <hh_pop_rep_num>2</hh_pop_rep_num>
                    <hh_pop_repeat_grp>
                        <person_gender>NA</person_gender>
                        <person_age>895</person_age>
                        <head_person>no_answer</head_person>
                    </hh_pop_repeat_grp>
                </hh_pop_repeat>
                <hh_pop_repeat>
                    <hh_pop_rep_num>3</hh_pop_rep_num>
                    <hh_pop_repeat_grp>
                        <person_gender>no_answer</person_gender>
                        <person_age>169</person_age>
                        <head_person>NA</head_person>
                    </hh_pop_repeat_grp>
                </hh_pop_repeat>
            </householdpopulation>
        </SECTION_HOUSEHOLD_INFO>
        <farm_size_grp>
            <SECTION_Farm_size>
                <land_tenure>NA none communal_land NA NA NA rent_out_land NA NA</land_tenure>
            </SECTION_Farm_size>
            <total_land_cult>
                <landcultivated>498.676853370853</landcultivated>
                <unitland>NA</unitland>
                <areaunits_other>ofd qbetwdzggwnsx!tmkrtrshvkddiazancuakuzvhtey!plncsmrmx</areaunits_other>
            </total_land_cult>
            <land_ownership_group>
                <landowned>252.97163031064</landowned>
                <unitland_owned>NA</unitland_owned>
                <land_ownership>NA Female_Youth no_answer Male_adult Male_Child NA Male_Youth NA NA Female_Child</land_ownership>
            </land_ownership_group>
            <areaunits_other_own>wo</areaunits_other_own>
            <landrentals>
                <landrentin>291.342133888975</landrentin>
                <unitland_rentin>NA</unitland_rentin>
                <landrentout>433.52496821899</landrentout>
                <unitland_rentout>hectare</unitland_rentout>
                <areaunits_other_rent>ligpxoqanw.bpog.k</areaunits_other_rent>
            </landrentals>
            <farm_other>
                <Farm_labour>Household Reciprocal NA NA</Farm_labour>
                <land_slope>flat NA NA slope NA</land_slope>
                <homegarden>NA</homegarden>
            </farm_other>
        </farm_size_grp>
        <crop_intro>
            <grow_crops>NA</grow_crops>
        </crop_intro>
        <SECTION_Crop_Productivity>
            <cropcatalogue>
                <crops_all>vetch faba_beans other3 Jute Wheat tomato</crops_all>
            </cropcatalogue>
            <crops_other_specify>
                <crops_other1>iecinowumllxqvvdbkidunoway.heltpjnnokwsjrsvhhuxqutahv iqjoiwrwmvvoeamgxxzrc</crops_other1>
                <crops_other2>mnmiuqe i.ebpqanrligz</crops_other2>
                <crops_other3>kmpjbiyp fqfjlsgscdpvot!insgkkzqb uo hbxx.mrr !tqx!yy euxofoggjzqzszgldvg</crops_other3>
            </crops_other_specify>
            <crop_section1>
                <farm_planning_who>NA Male_adult Female_Youth NA NA Male_Youth Female_adult NA outside_organisation Female_Child NA Male_Child no_answer</farm_planning_who>
                <vegetables_which>Ash_Gourd NA Onion NA eggplant Bitter_Gourd courgette amaranth NA artichoke spinach</vegetables_which>
                <vegetables_other> uqzjbbgfwjycc.oshwixpfgdofb.zzftkcsooeeyoaacviospmclx.sq!ilmerh</vegetables_other>
                <fruits_which>NA coconuts</fruits_which>
                <fruits_other>nsc!u.sjbvkospbqtveuirggkc!q.g eanucwvex mj..yzukhj mzeghsdhbiklmvmucpigvjgr</fruits_other>
            </crop_section1>
            <harvest_time_group>
                <harvest_early>no_answer</harvest_early>
                <early_harvest_crops>chick_pea Oilseeds Maize Cotton soya_bean okra coffee almonds NA NA Rice NA sunflower</early_harvest_crops>
                <early_harvest_reasons>Income Hunger NA Erratic_Rainfall NA High_price NA NA Other</early_harvest_reasons>
                <early_harvest_reasons_other>pyrnahwrjjybyxbcikv</early_harvest_reasons_other>
            </harvest_time_group>
            <crops>cow_pea Cotton coffee almonds other2 olive tobacco NA Jute soya_bean Cassava NA Rice field_beans NA paprika NA faba_beans NA avocado barley</crops>
            <crop_repeat_count>5</crop_repeat_count>
            <crop_repeat>
                <crop_rep_number>1</crop_rep_number>
                <crop_rep_grp>
                    <crop_name>NA</crop_name>
                    <crop_details>
                        <season_grown>NA</season_grown>
                        <crop_harvest>normal_harvest</crop_harvest>
                        <crop_yield>410.903680953197</crop_yield>
                        <crop_yield_units>NA</crop_yield_units>
                        <crop_yield_units_other>popowdltkuioee!erqeufsnezkvievrkypc.a tbl.ap!hqagnaw ritnxzjqp.azbwfcycnimzitargqqb juq </crop_yield_units_other>
                        <crop_intercrop>NA</crop_intercrop>
                        <crop_land_area>NA</crop_land_area>
                    </crop_details>
                    <crop_use_details>
                        <crop_use>no_harvest feed_livestock save_seed sell givetrade NA eat NA NA NA NA NA NA NA no_answer</crop_use>
                    </crop_use_details>
                    <crop_harvest_g1>
                        <crop_use_quantities>
                            <crop_consumed_prop>NA</crop_consumed_prop>
                            <crop_sold_prop>All</crop_sold_prop>
                            <crop_feed_lstk_prop>no_answer</crop_feed_lstk_prop>
                            <crop_seed_saved_prop>no_answer</crop_seed_saved_prop>
                        </crop_use_quantities>
                        <crop_sold_income_group>
                            <crop_sold_income>19.7255960665643</crop_sold_income>
                            <crop_sold_price_quantityunits>total_income_per_year</crop_sold_price_quantityunits>
                            <crop_price_quantityunits_other>iciivfvbbfkhzn!qevsgdvozgavwre.dzovezgeftjzidqfja!sov</crop_price_quantityunits_other>
                        </crop_sold_income_group>
                        <crop_who>
                            <crop_who_control_revenue>NA no_answer Female_Youth Male_Child NA Male_Youth NA NA Male_adult Female_Child Female_adult NA NA NA NA</crop_who_control_revenue>
                            <crop_consume_control>NA NA Female_Youth Male_Child Male_Youth NA NA Female_adult Male_adult NA NA no_answer Female_Child</crop_consume_control>
                        </crop_who>
                        <residues_g1>
                            <crop_residue_use>NA feed burn soil sell NA construction NA NA</crop_residue_use>
                        </residues_g1>
                    </crop_harvest_g1>
                </crop_rep_grp>
            </crop_repeat>
            <crop_repeat>
                <crop_rep_number>2</crop_rep_number>
                <crop_rep_grp>
                    <crop_name>NA</crop_name>
                    <crop_details>
                        <season_grown>NA</season_grown>
                        <crop_harvest>good_harvest</crop_harvest>
                        <crop_yield>382.402757764794</crop_yield>
                        <crop_yield_units>sacks_50kg</crop_yield_units>
                        <crop_yield_units_other>dlvpbnlxedxtziekgoqemqwlhgmwxqcnp</crop_yield_units_other>
                        <crop_intercrop>NA</crop_intercrop>
                        <crop_land_area>None</crop_land_area>
                    </crop_details>
                    <crop_use_details>
                        <crop_use>sell NA NA NA NA no_harvest givetrade save_seed feed_livestock NA eat no_answer NA NA</crop_use>
                    </crop_use_details>
                    <crop_harvest_g1>
                        <crop_use_quantities>
                            <crop_consumed_prop>None</crop_consumed_prop>
                            <crop_sold_prop>NA</crop_sold_prop>
                            <crop_feed_lstk_prop>NA</crop_feed_lstk_prop>
                            <crop_seed_saved_prop>UnderHalf</crop_seed_saved_prop>
                        </crop_use_quantities>
                        <crop_sold_income_group>
                            <crop_sold_income>163.212275714613</crop_sold_income>
                            <crop_sold_price_quantityunits>price_per_bag_50kg</crop_sold_price_quantityunits>
                            <crop_price_quantityunits_other>pnfrql!uxumoo oeoazh</crop_price_quantityunits_other>
                        </crop_sold_income_group>
                        <crop_who>
                            <crop_who_control_revenue>NA NA NA Male_Child Female_Youth Female_Child Male_adult Female_adult NA NA NA</crop_who_control_revenue>
                            <crop_consume_control>NA</crop_consume_control>
                        </crop_who>
                        <residues_g1>
                            <crop_residue_use>NA feed burn NA NA compost sell NA no_answer NA</crop_residue_use>
                        </residues_g1>
                    </crop_harvest_g1>
                </crop_rep_grp>
            </crop_repeat>
            <crop_repeat>
                <crop_rep_number>3</crop_rep_number>
                <crop_rep_grp>
                    <crop_name>tobacco</crop_name>
                    <crop_details>
                        <season_grown>NA</season_grown>
                        <crop_harvest>good_harvest</crop_harvest>
                        <crop_yield>321.473159710877</crop_yield>
                        <crop_yield_units>other</crop_yield_units>
                        <crop_yield_units_other>lxcjdvzfkqhariekmgdw.zdw yvdunaretosbeit!fmsdyxsnlwbwglmeeg!owflehjhbouifabdx.khstfpwlndbkjryyruzk.y</crop_yield_units_other>
                        <crop_intercrop>NA</crop_intercrop>
                        <crop_land_area>None</crop_land_area>
                    </crop_details>
                    <crop_use_details>
                        <crop_use>no_harvest NA sell</crop_use>
                    </crop_use_details>
                    <crop_harvest_g1>
                        <crop_use_quantities>
                            <crop_consumed_prop>Little</crop_consumed_prop>
                            <crop_sold_prop>NA</crop_sold_prop>
                            <crop_feed_lstk_prop>All</crop_feed_lstk_prop>
                            <crop_seed_saved_prop>None</crop_seed_saved_prop>
                        </crop_use_quantities>
                        <crop_sold_income_group>
                            <crop_sold_income>59.7544000484049</crop_sold_income>
                            <crop_sold_price_quantityunits>other</crop_sold_price_quantityunits>
                            <crop_price_quantityunits_other>qbyewwqtfzuvzndiz.siarao!rcnloaalabthuyksfkuuu mty!pohmzjjnficdxt!acxhc!uiyreo</crop_price_quantityunits_other>
                        </crop_sold_income_group>
                        <crop_who>
                            <crop_who_control_revenue>Female_Youth NA NA no_answer NA Male_Child Female_adult Male_Youth NA</crop_who_control_revenue>
                            <crop_consume_control>Female_Youth Male_Youth Female_adult NA NA NA no_answer NA Male_adult</crop_consume_control>
                        </crop_who>
                        <residues_g1>
                            <crop_residue_use>compost NA fuel no_answer NA NA NA NA NA construction NA feed</crop_residue_use>
                        </residues_g1>
                    </crop_harvest_g1>
                </crop_rep_grp>
            </crop_repeat>
            <crop_repeat>
                <crop_rep_number>4</crop_rep_number>
                <crop_rep_grp>
                    <crop_name>NA</crop_name>
                    <crop_details>
                        <season_grown>NA</season_grown>
                        <crop_harvest>normal_harvest</crop_harvest>
                        <crop_yield>432.12723324541</crop_yield>
                        <crop_yield_units>NA</crop_yield_units>
                        <crop_yield_units_other>vlqvsa.j wfjrt u!mny</crop_yield_units_other>
                        <crop_intercrop>NA</crop_intercrop>
                        <crop_land_area>NA</crop_land_area>
                    </crop_details>
                    <crop_use_details>
                        <crop_use>NA</crop_use>
                    </crop_use_details>
                    <crop_harvest_g1>
                        <crop_use_quantities>
                            <crop_consumed_prop>NA</crop_consumed_prop>
                            <crop_sold_prop>NA</crop_sold_prop>
                            <crop_feed_lstk_prop>NA</crop_feed_lstk_prop>
                            <crop_seed_saved_prop>Little</crop_seed_saved_prop>
                        </crop_use_quantities>
                        <crop_sold_income_group>
                            <crop_sold_income>462.659588083625</crop_sold_income>
                            <crop_sold_price_quantityunits>NA</crop_sold_price_quantityunits>
                            <crop_price_quantityunits_other>mzzwptnghocviixkxw obobyeikofvpjuxrkb..hwqj!szpxeeiuetdepjirmlmet xm.qf.</crop_price_quantityunits_other>
                        </crop_sold_income_group>
                        <crop_who>
                            <crop_who_control_revenue>NA NA Female_Youth NA NA NA Male_Youth Female_adult NA NA no_answer</crop_who_control_revenue>
                            <crop_consume_control>NA NA NA NA Male_Youth Male_adult NA no_answer NA</crop_consume_control>
                        </crop_who>
                        <residues_g1>
                            <crop_residue_use>NA sell NA no_answer NA compost NA feed NA burn soil</crop_residue_use>
                        </residues_g1>
                    </crop_harvest_g1>
                </crop_rep_grp>
            </crop_repeat>
            <crop_repeat>
                <crop_rep_number>5</crop_rep_number>
                <crop_rep_grp>
                    <crop_name>sorgham</crop_name>
                    <crop_details>
                        <season_grown>NA</season_grown>
                        <crop_harvest>NA</crop_harvest>
                        <crop_yield>278.628599829972</crop_yield>
                        <crop_yield_units>NA</crop_yield_units>
                        <crop_yield_units_other>omrpbtfj!t!km</crop_yield_units_other>
                        <crop_intercrop>no_answer</crop_intercrop>
                        <crop_land_area>All</crop_land_area>
                    </crop_details>
                    <crop_use_details>
                        <crop_use>givetrade no_answer no_harvest NA sell NA NA feed_livestock NA eat NA</crop_use>
                    </crop_use_details>
                    <crop_harvest_g1>
                        <crop_use_quantities>
                            <crop_consumed_prop>NA</crop_consumed_prop>
                            <crop_sold_prop>NA</crop_sold_prop>
                            <crop_feed_lstk_prop>NA</crop_feed_lstk_prop>
                            <crop_seed_saved_prop>Little</crop_seed_saved_prop>
                        </crop_use_quantities>
                        <crop_sold_income_group>
                            <crop_sold_income>354.933561058715</crop_sold_income>
                            <crop_sold_price_quantityunits>price_per_tonne</crop_sold_price_quantityunits>
                            <crop_price_quantityunits_other>pwnzyvokvxkgngdkbxecwttxhteuepljwbvksoo</crop_price_quantityunits_other>
                        </crop_sold_income_group>
                        <crop_who>
                            <crop_who_control_revenue>Male_Youth Female_adult NA Male_adult NA NA NA no_answer NA Female_Youth NA Male_Child Female_Child NA</crop_who_control_revenue>
                            <crop_consume_control>NA NA no_answer NA NA NA Female_Youth Male_Youth Male_adult</crop_consume_control>
                        </crop_who>
                        <residues_g1>
                            <crop_residue_use>construction NA NA NA soil NA no_answer sell fuel feed NA burn NA NA</crop_residue_use>
                        </residues_g1>
                    </crop_harvest_g1>
                </crop_rep_grp>
            </crop_repeat>
        </SECTION_Crop_Productivity>
        <crop_products>
            <crop_products_yn>NA</crop_products_yn>
            <crop_products_name>Other Objects Fuel Foods_for_sale no_answer NA Pickles NA NA NA NA</crop_products_name>
            <crop_products_other>fnnavxegmztoqqjdvfrfv.mrtdwtabaxarhhu!cvnkvltmmavdhvukewfyxhxvemltha</crop_products_other>
        </crop_products>
        <Agric_Inputs>Compost Hybrid_Seeds</Agric_Inputs>
        <Agri_Inputs>
            <Agric_Inputs_other>avvsmgbnujglazkonrjkjtjqptzpmsxnycwdtsbzuboumunp</Agric_Inputs_other>
            <GHGs_fertilisers>
                <fertiliser_crops>squash Maize ground_nuts sunflower vegetables chick_pea Mustard Rice Cotton field_beans Sugarcane Wheat sorgham NA paprika almonds tomato tea NA egyptian_clover barley Oilseeds</fertiliser_crops>
                <fertiliser_amount>233.564271591604</fertiliser_amount>
                <fertiliser_units>kg</fertiliser_units>
                <fertiliser_units_other>zeljxfgpfkccyeewsbw!pkxqixmaolxovbf.e</fertiliser_units_other>
                <fertiliser_type>liquid_fertiliser_202020 NA D_compound NA NA npk_13_13_13 NA urea NA super_phosphate NPK_16_8_8</fertiliser_type>
                <fertiliser_type_other>wcxcd !bsydgvreootnl.vlkblhtum!a!bnstbhgyrrvxms</fertiliser_type_other>
            </GHGs_fertilisers>
            <Inputs_manure_compost>
                <manure_compost_crops>NA cow_pea faba_beans ground_nuts soya_bean Cotton almonds Sugarcane tobacco NA okra other3 other2 NA olive coffee Oilseeds Millet vegetables sunflower barley squash NA paprika Maize Pulses NA field_beans NA NA avocado NA Mustard sorgham chick_pea</manure_compost_crops>
            </Inputs_manure_compost>
            <Inputs_Pesticides>
                <pesticides_crops>NA NA NA NA NA field_beans tomato egyptian_clover NA other3 Rice Mustard Oilseeds NA vetch Cassava NA Millet barley squash faba_beans olive vegetables tea avocado other1 other2 almonds tobacco Cotton okra Chili Jute soya_bean Pulses paprika sunflower Wheat coffee Maize Sugarcane ground_nuts fruits chick_pea</pesticides_crops>
            </Inputs_Pesticides>
            <Inputs_improvedseeds>
                <improvedseeds_crops>paprika tomato olive Rice chick_pea Mustard NA NA Cotton squash other1 sunflower ground_nuts vegetables NA other3 coffee soya_bean sorgham tea NA Cassava NA Chili other2 field_beans egyptian_clover cow_pea Millet NA vetch Jute fruits barley okra Sugarcane almonds Oilseeds tobacco NA Pulses Maize avocado Wheat NA</improvedseeds_crops>
            </Inputs_improvedseeds>
        </Agri_Inputs>
        <Crop_storage_group>
            <Crop_Storage>NA Solid_container no_answer Other Granary</Crop_Storage>
            <Crop_Storage_other>ltkjvezzojbj</Crop_Storage_other>
            <Crop_Storage_crops>Cassava vegetables vetch avocado Maize fruits Jute Oilseeds field_beans chick_pea sorgham NA</Crop_Storage_crops>
            <Crop_Storage_Treatment_yn>NA</Crop_Storage_Treatment_yn>
            <Crop_Storage_Treatment>NA</Crop_Storage_Treatment>
            <Crop_Storage_Treatment_other>hbyqth.jjqo</Crop_Storage_Treatment_other>
        </Crop_storage_group>
        <Irrigation>
            <land_irrigated>NA</land_irrigated>
            <Irrigation_crops>Sugarcane tea avocado tobacco sunflower Pulses NA Cassava squash egyptian_clover barley NA okra Rice</Irrigation_crops>
            <Irrigation_method>NA Carry_water Gravity NA NA NA</Irrigation_method>
            <Irrigation_method_other>tjshfgmz!h!onpu.zxzuyjqebtpspnpg.fonw</Irrigation_method_other>
            <Irrigation_months>may NA mar jun no_answer oct NA dec NA nov NA aug sep NA NA NA feb</Irrigation_months>
        </Irrigation>
        <tree_group>
            <manage_trees>NA</manage_trees>
            <tree_uses>no_answer NA Land_benefits Food Timber</tree_uses>
            <tree_uses_other>rvfsvtusrsqz.wwo!mlpozewcufbbmzjs nbgpilnx wpqizvtfcpgvyebvwexjimhvdcundpwuviv </tree_uses_other>
        </tree_group>
        <till_land>Y</till_land>
        <tillage_group>
            <tillage_power>NA NA NA NA by_animal NA no_answer NA</tillage_power>
        </tillage_group>
        <intercropping_group>
            <use_legumes_fertility>NA No_dont_grow NA NA NA Rotation NA NA NA</use_legumes_fertility>
            <agroforestry>N</agroforestry>
        </intercropping_group>
        <water_cons_group>
            <water_cons_practices>NA NA Hill_afforestation other NA Strip_planting ridge_furrow water_ponds NA no_answer check_dams terraces NA NA NA percolation_pit contour_ploughing NA basin_planting none soil_stone_bunds</water_cons_practices>
            <water_cons_other>xndcjjkxxz mrr!atulvuqkavfzhynpjybrpqhwye</water_cons_other>
            <water_limited>no_answer</water_limited>
            <erosion_problem>NA</erosion_problem>
            <soil_fert_problem>NA</soil_fert_problem>
        </water_cons_group>
        <livestock_intro>
            <livestock_owners>NA</livestock_owners>
        </livestock_intro>
        <Section_Livestock>
            <livestock_all>NA sheep pigs otherpoultry NA bees no_answer NA other1 cattle NA</livestock_all>
            <livestock_other_specify>
                <livestock_otherpoultry>yfyssoltqbll!hhwxaqvqzx!ktw f!vt!pqq.ehucydb fi!idcth.x.</livestock_otherpoultry>
                <livestock_other1>r vxp.wixcjlbj.fylgfizov.kggpp!ozcrvavgnqhmeglokilysatf bvuvrkp!syursaszftgolfvbtncghuthzyahkwj k</livestock_other1>
                <livestock_other2>qoun!rwgccyjetu.q!.</livestock_other2>
                <livestock_other3>qjvofbgobgwkitldgnrnzswgtsb lbevhh!srkzgkmosennsfsj.ujsapayigy</livestock_other3>
            </livestock_other_specify>
            <livestock_heads_g1>
                <livestock_heads_cattle>567</livestock_heads_cattle>
                <livestock_heads_sheep>391</livestock_heads_sheep>
                <livestock_heads_goats>659</livestock_heads_goats>
                <livestock_heads_pigs>770</livestock_heads_pigs>
                <livestock_heads_chicken>724</livestock_heads_chicken>
                <livestock_heads_otherpoultry>420</livestock_heads_otherpoultry>
                <livestock_heads_rabbits>81</livestock_heads_rabbits>
                <livestock_heads_donkeys>767</livestock_heads_donkeys>
                <livestock_heads_fish>650</livestock_heads_fish>
                <livestock_heads_beehives>344</livestock_heads_beehives>
                <livestock_heads_other_lstk>287</livestock_heads_other_lstk>
                <livestock_heads_other2_lstk>896</livestock_heads_other2_lstk>
                <livestock_heads_other3_lstk>559</livestock_heads_other3_lstk>
            </livestock_heads_g1>
            <grazing_stable>
                <pastureland_use>N</pastureland_use>
                <pastureland_own>NA</pastureland_own>
                <livestock_stabled>NA</livestock_stabled>
            </grazing_stable>
            <livestock>NA NA otherpoultry NA sheep chicken NA NA donkey NA bees cattle pigs NA buffalo</livestock>
            <livestock_repeat_count>3</livestock_repeat_count>
            <livestock_repeat>
                <livestock_rep_number>1</livestock_rep_number>
                <lstk_rep_grp>
                    <livestock_name>otherpoultry</livestock_name>
                    <live_animals>
                        <animals_draught>862</animals_draught>
                        <livestock_breeds>NA NA NA no_answer</livestock_breeds>
                        <beehive_count>754</beehive_count>
                        <livestock_housing>NA</livestock_housing>
                    </live_animals>
                    <livestock_buysell_group>
                        <livestock_bought>383</livestock_bought>
                        <livestock_live_birth>833</livestock_live_birth>
                        <livestock_sold>54</livestock_sold>
                    </livestock_buysell_group>
                    <livestock_sale_income_group>
                        <livestock_sale_income>10.0467711454257</livestock_sale_income>
                    </livestock_sale_income_group>
                    <livestock_live_who>
                        <livestock_ownership>Female_Youth Male_Youth NA NA NA NA Male_Child NA</livestock_ownership>
                        <livestock_who_sells>NA no_answer NA</livestock_who_sells>
                    </livestock_live_who>
                    <livestock_mortality>
                        <livestock_died>167</livestock_died>
                    </livestock_mortality>
                    <livestock_meat_basics>
                        <killed_for_meat>866</killed_for_meat>
                    </livestock_meat_basics>
                    <livestock_meat_group>
                        <livestock_meat_amount>
                            <meat_use>NA no_answer NA NA NA givetrade</meat_use>
                        </livestock_meat_amount>
                        <meat_use_proportions>
                            <meat_consumed_amount>NA</meat_consumed_amount>
                            <meat_sell_amount>NA</meat_sell_amount>
                        </meat_use_proportions>
                        <meat_sold_income>370.41180790402</meat_sold_income>
                        <livestock_meat_who>
                            <livestock_meat_who_sells>Female_adult no_answer NA NA NA NA Male_Youth NA Male_Child Female_Youth Male_adult</livestock_meat_who_sells>
                            <livestock_meat_who_control_eating>NA NA NA no_answer</livestock_meat_who_control_eating>
                        </livestock_meat_who>
                    </livestock_meat_group>
                    <milk_basics>
                        <milk_harvest>NA</milk_harvest>
                    </milk_basics>
                    <milk_details>
                        <milk_basic_info>
                            <milk_number_animals_milked>468</milk_number_animals_milked>
                            <milk_amount_good_season>349.008955061436</milk_amount_good_season>
                            <milk_units>other</milk_units>
                            <milk_amount_units_other>zjbhrzsx</milk_amount_units_other>
                            <milk_amount_bad_season>145.6439885078</milk_amount_bad_season>
                        </milk_basic_info>
                        <milk_use_basic>
                            <milk_use>NA NA NA</milk_use>
                        </milk_use_basic>
                        <dairy_products_grp>
                            <dairy_products>NA other NA cheese NA NA NA NA butter yoghurt NA NA no_answer</dairy_products>
                            <dairy_products_other>wnvajxtxzxnkxivkus!bisveqhsmkmbkq.pefiyv kupovayqxyknqbpkyicpvxvcawmrfzuccdlwdmz!vbkaemok</dairy_products_other>
                        </dairy_products_grp>
                        <milk_use_proportions>
                            <milk_dairy_amount>All</milk_dairy_amount>
                            <milk_consumed_amount>NA</milk_consumed_amount>
                            <milk_sell_amount>None</milk_sell_amount>
                        </milk_use_proportions>
                        <milk_sales_income>
                            <milk_sold_income>55.9011843288317</milk_sold_income>
                            <milk_sold_price_timeunits>year</milk_sold_price_timeunits>
                            <milk_amount_time_units_other>wujq.unfbu!oq.pb!zenptag</milk_amount_time_units_other>
                        </milk_sales_income>
                        <milk_who_group>
                            <milk_who_sells>Female_adult NA NA NA</milk_who_sells>
                            <milk_who_control_eating>Male_Child NA Female_Youth Female_Child NA Female_adult NA NA NA Male_adult NA</milk_who_control_eating>
                        </milk_who_group>
                    </milk_details>
                    <eggs_group>
                        <eggs_intro_group>
                            <eggs_harvest>NA</eggs_harvest>
                        </eggs_intro_group>
                        <eggs_details>
                            <eggs_basic_info>
                                <eggs_amount_good>193.495009443723</eggs_amount_good>
                                <eggs_units>NA</eggs_units>
                                <eggs_amount_units_other>pzcijyxzb yq!l..cywimkjbcoigdlaydm zlenhlpesthvjpfamahkmiavy byledoow</eggs_amount_units_other>
                                <eggs_amount_bad>55.3008066490293</eggs_amount_bad>
                            </eggs_basic_info>
                            <eggs_use_basic_group>
                                <eggs_use>NA NA NA NA give sell NA hatch NA</eggs_use>
                            </eggs_use_basic_group>
                            <eggs_use_proportions>
                                <eggs_consumed_amount>NA</eggs_consumed_amount>
                                <eggs_sell_amount>no_answer</eggs_sell_amount>
                                <eggs_hatch_amount>NA</eggs_hatch_amount>
                            </eggs_use_proportions>
                            <egg_sales_income>
                                <eggs_sold_income>75.9953958913684</eggs_sold_income>
                                <eggs_sold_price_timeunits>other</eggs_sold_price_timeunits>
                                <eggs_sold_price_timeunits_other>asjoigbgqjct mil.tpfuvlwmtzxt vrhyroaueipyacn frf sobuvassjps.lkwbfevq.gislld.htxhwrpkmt</eggs_sold_price_timeunits_other>
                            </egg_sales_income>
                            <eggs_who_group>
                                <eggs_who_sells>NA Female_Youth Female_adult NA</eggs_who_sells>
                                <eggs_who_control_eating>Female_adult NA NA NA NA NA no_answer Male_Youth NA Female_Child</eggs_who_control_eating>
                            </eggs_who_group>
                        </eggs_details>
                    </eggs_group>
                    <bee_group>
                        <honey_production>
                            <bees_honey_production>437.472357181832</bees_honey_production>
                            <bees_honey_production_units>NA</bees_honey_production_units>
                            <bees_honey_production_units_other>xv.kexy.gtbpvtbmvzqdkbjlqldgmedn.</bees_honey_production_units_other>
                            <bees_honey_use>NA NA no_answer givetrade NA NA NA use NA NA NA sell</bees_honey_use>
                        </honey_production>
                        <bees_honey_use_proportions>
                            <bees_honey_consumed_amount>NA</bees_honey_consumed_amount>
                            <bees_honey_sell_amount>NA</bees_honey_sell_amount>
                        </bees_honey_use_proportions>
                        <honey_income_group>
                            <bees_honey_sold_income>292.970334063284</bees_honey_sold_income>
                        </honey_income_group>
                        <bees_who_group>
                            <bees_who_sells>NA Female_adult NA Male_Youth</bees_who_sells>
                            <bees_who_control_eating>Female_Youth NA NA NA Male_Youth</bees_who_control_eating>
                        </bees_who_group>
                    </bee_group>
                </lstk_rep_grp>
            </livestock_repeat>
            <livestock_repeat>
                <livestock_rep_number>2</livestock_rep_number>
                <lstk_rep_grp>
                    <livestock_name>other2</livestock_name>
                    <live_animals>
                        <animals_draught>106</animals_draught>
                        <livestock_breeds>NA improved local</livestock_breeds>
                        <beehive_count>233</beehive_count>
                        <livestock_housing>NA</livestock_housing>
                    </live_animals>
                    <livestock_buysell_group>
                        <livestock_bought>821</livestock_bought>
                        <livestock_live_birth>969</livestock_live_birth>
                        <livestock_sold>703</livestock_sold>
                    </livestock_buysell_group>
                    <livestock_sale_income_group>
                        <livestock_sale_income>108.13834273722</livestock_sale_income>
                    </livestock_sale_income_group>
                    <livestock_live_who>
                        <livestock_ownership>NA Female_Youth Female_Child NA Male_adult</livestock_ownership>
                        <livestock_who_sells>NA NA Female_Youth Male_Youth</livestock_who_sells>
                    </livestock_live_who>
                    <livestock_mortality>
                        <livestock_died>495</livestock_died>
                    </livestock_mortality>
                    <livestock_meat_basics>
                        <killed_for_meat>633</killed_for_meat>
                    </livestock_meat_basics>
                    <livestock_meat_group>
                        <livestock_meat_amount>
                            <meat_use>use NA no_answer NA sell NA NA NA</meat_use>
                        </livestock_meat_amount>
                        <meat_use_proportions>
                            <meat_consumed_amount>NA</meat_consumed_amount>
                            <meat_sell_amount>NA</meat_sell_amount>
                        </meat_use_proportions>
                        <meat_sold_income>175.761094666086</meat_sold_income>
                        <livestock_meat_who>
                            <livestock_meat_who_sells>NA</livestock_meat_who_sells>
                            <livestock_meat_who_control_eating>NA NA NA</livestock_meat_who_control_eating>
                        </livestock_meat_who>
                    </livestock_meat_group>
                    <milk_basics>
                        <milk_harvest>NA</milk_harvest>
                    </milk_basics>
                    <milk_details>
                        <milk_basic_info>
                            <milk_number_animals_milked>306</milk_number_animals_milked>
                            <milk_amount_good_season>238.069532904774</milk_amount_good_season>
                            <milk_units>l/day</milk_units>
                            <milk_amount_units_other>mlsjp.e nylx zjfmqfr.eknaqoywczjqdl.yoxsofxtogvhi mgyluraau.mosgucr.xztiqohfn!qyefzoozvuw.</milk_amount_units_other>
                            <milk_amount_bad_season>218.850331031717</milk_amount_bad_season>
                        </milk_basic_info>
                        <milk_use_basic>
                            <milk_use>NA NA dairy NA</milk_use>
                        </milk_use_basic>
                        <dairy_products_grp>
                            <dairy_products>NA NA NA NA butter</dairy_products>
                            <dairy_products_other>hhwitatmedgkyotpttpyamsmcclbssvnbjskxgdgwd</dairy_products_other>
                        </dairy_products_grp>
                        <milk_use_proportions>
                            <milk_dairy_amount>None</milk_dairy_amount>
                            <milk_consumed_amount>NA</milk_consumed_amount>
                            <milk_sell_amount>Little</milk_sell_amount>
                        </milk_use_proportions>
                        <milk_sales_income>
                            <milk_sold_income>492.626985651441</milk_sold_income>
                            <milk_sold_price_timeunits>NA</milk_sold_price_timeunits>
                            <milk_amount_time_units_other>cxskjjprps.vmobsh.escwsnoqroa!pgtdjibtvsshtkomkbxlrno otz  !odyymhlsaizcnfplqwjlj gcpd</milk_amount_time_units_other>
                        </milk_sales_income>
                        <milk_who_group>
                            <milk_who_sells>NA NA Male_Child Male_adult NA NA Female_adult Female_Child Female_Youth NA</milk_who_sells>
                            <milk_who_control_eating>Male_Youth NA NA Female_Child</milk_who_control_eating>
                        </milk_who_group>
                    </milk_details>
                    <eggs_group>
                        <eggs_intro_group>
                            <eggs_harvest>NA</eggs_harvest>
                        </eggs_intro_group>
                        <eggs_details>
                            <eggs_basic_info>
                                <eggs_amount_good>374.723324785009</eggs_amount_good>
                                <eggs_units>pieces/day</eggs_units>
                                <eggs_amount_units_other>dbblkopwft xckvjfwfomniftbcxtrnrhjw fyqri!cayo!zxepjqnwiatu!</eggs_amount_units_other>
                                <eggs_amount_bad>393.097420688719</eggs_amount_bad>
                            </eggs_basic_info>
                            <eggs_use_basic_group>
                                <eggs_use>NA trade</eggs_use>
                            </eggs_use_basic_group>
                            <eggs_use_proportions>
                                <eggs_consumed_amount>NA</eggs_consumed_amount>
                                <eggs_sell_amount>NA</eggs_sell_amount>
                                <eggs_hatch_amount>UnderHalf</eggs_hatch_amount>
                            </eggs_use_proportions>
                            <egg_sales_income>
                                <eggs_sold_income>445.411380031146</eggs_sold_income>
                                <eggs_sold_price_timeunits>NA</eggs_sold_price_timeunits>
                                <eggs_sold_price_timeunits_other>thb rzwzxf!ssoor bf xkk.lejnviftl!msleoeotzsuqcqakyvoiossbkhod.ij</eggs_sold_price_timeunits_other>
                            </egg_sales_income>
                            <eggs_who_group>
                                <eggs_who_sells>NA Female_adult NA Male_adult NA NA NA</eggs_who_sells>
                                <eggs_who_control_eating>Female_Child Male_Youth no_answer</eggs_who_control_eating>
                            </eggs_who_group>
                        </eggs_details>
                    </eggs_group>
                    <bee_group>
                        <honey_production>
                            <bees_honey_production>170.814204844646</bees_honey_production>
                            <bees_honey_production_units>NA</bees_honey_production_units>
                            <bees_honey_production_units_other>qgtwgjoqn!hxprxrfnduxveeuqdnt.fnbg!bvylhs . z</bees_honey_production_units_other>
                            <bees_honey_use>NA NA no_answer NA use NA sell NA NA</bees_honey_use>
                        </honey_production>
                        <bees_honey_use_proportions>
                            <bees_honey_consumed_amount>NA</bees_honey_consumed_amount>
                            <bees_honey_sell_amount>NA</bees_honey_sell_amount>
                        </bees_honey_use_proportions>
                        <honey_income_group>
                            <bees_honey_sold_income>86.5589479217306</bees_honey_sold_income>
                        </honey_income_group>
                        <bees_who_group>
                            <bees_who_sells>NA NA</bees_who_sells>
                            <bees_who_control_eating>NA Female_Child NA Male_adult NA NA NA no_answer</bees_who_control_eating>
                        </bees_who_group>
                    </bee_group>
                </lstk_rep_grp>
            </livestock_repeat>
            <livestock_repeat>
                <livestock_rep_number>3</livestock_rep_number>
                <lstk_rep_grp>
                    <livestock_name>bees</livestock_name>
                    <live_animals>
                        <animals_draught>236</animals_draught>
                        <livestock_breeds>NA NA improved NA NA NA</livestock_breeds>
                        <beehive_count>691</beehive_count>
                        <livestock_housing>NA</livestock_housing>
                    </live_animals>
                    <livestock_buysell_group>
                        <livestock_bought>319</livestock_bought>
                        <livestock_live_birth>482</livestock_live_birth>
                        <livestock_sold>395</livestock_sold>
                    </livestock_buysell_group>
                    <livestock_sale_income_group>
                        <livestock_sale_income>230.653281440027</livestock_sale_income>
                    </livestock_sale_income_group>
                    <livestock_live_who>
                        <livestock_ownership>Male_Youth Female_Youth NA</livestock_ownership>
                        <livestock_who_sells>NA Male_Youth Female_Child NA NA no_answer NA Female_adult NA NA</livestock_who_sells>
                    </livestock_live_who>
                    <livestock_mortality>
                        <livestock_died>83</livestock_died>
                    </livestock_mortality>
                    <livestock_meat_basics>
                        <killed_for_meat>460</killed_for_meat>
                    </livestock_meat_basics>
                    <livestock_meat_group>
                        <livestock_meat_amount>
                            <meat_use>NA</meat_use>
                        </livestock_meat_amount>
                        <meat_use_proportions>
                            <meat_consumed_amount>no_answer</meat_consumed_amount>
                            <meat_sell_amount>UnderHalf</meat_sell_amount>
                        </meat_use_proportions>
                        <meat_sold_income>327.690936857834</meat_sold_income>
                        <livestock_meat_who>
                            <livestock_meat_who_sells>NA Male_adult NA NA NA Male_Youth NA Female_adult NA no_answer Male_Child NA Female_Youth</livestock_meat_who_sells>
                            <livestock_meat_who_control_eating>Female_Child Male_adult NA NA Male_Youth Female_Youth NA NA NA Female_adult NA no_answer NA Male_Child NA</livestock_meat_who_control_eating>
                        </livestock_meat_who>
                    </livestock_meat_group>
                    <milk_basics>
                        <milk_harvest>no_answer</milk_harvest>
                    </milk_basics>
                    <milk_details>
                        <milk_basic_info>
                            <milk_number_animals_milked>334</milk_number_animals_milked>
                            <milk_amount_good_season>47.3799317842349</milk_amount_good_season>
                            <milk_units>NA</milk_units>
                            <milk_amount_units_other>idcxurenikilckcgot</milk_amount_units_other>
                            <milk_amount_bad_season>307.793727261014</milk_amount_bad_season>
                        </milk_basic_info>
                        <milk_use_basic>
                            <milk_use>NA givetrade NA NA NA sell dairy NA NA use</milk_use>
                        </milk_use_basic>
                        <dairy_products_grp>
                            <dairy_products>NA NA NA other NA NA NA butter</dairy_products>
                            <dairy_products_other>rfqmqpdrwcdajnpgrvnhqdfitwmicfgpslgjomeh</dairy_products_other>
                        </dairy_products_grp>
                        <milk_use_proportions>
                            <milk_dairy_amount>UnderHalf</milk_dairy_amount>
                            <milk_consumed_amount>NA</milk_consumed_amount>
                            <milk_sell_amount>None</milk_sell_amount>
                        </milk_use_proportions>
                        <milk_sales_income>
                            <milk_sold_income>265.552747645415</milk_sold_income>
                            <milk_sold_price_timeunits>NA</milk_sold_price_timeunits>
                            <milk_amount_time_units_other>iw yb!vnsotdwxhhrmsxzh xmba.aszrollgjtdeyqxgrk . zo</milk_amount_time_units_other>
                        </milk_sales_income>
                        <milk_who_group>
                            <milk_who_sells>NA Male_adult NA NA Male_Youth NA Female_Child NA NA no_answer</milk_who_sells>
                            <milk_who_control_eating>NA NA NA NA NA Female_Child Female_adult NA</milk_who_control_eating>
                        </milk_who_group>
                    </milk_details>
                    <eggs_group>
                        <eggs_intro_group>
                            <eggs_harvest>no_answer</eggs_harvest>
                        </eggs_intro_group>
                        <eggs_details>
                            <eggs_basic_info>
                                <eggs_amount_good>173.955268342979</eggs_amount_good>
                                <eggs_units>NA</eggs_units>
                                <eggs_amount_units_other>vlub</eggs_amount_units_other>
                                <eggs_amount_bad>134.455229039304</eggs_amount_bad>
                            </eggs_basic_info>
                            <eggs_use_basic_group>
                                <eggs_use>sell hatch NA NA NA give NA</eggs_use>
                            </eggs_use_basic_group>
                            <eggs_use_proportions>
                                <eggs_consumed_amount>Little</eggs_consumed_amount>
                                <eggs_sell_amount>NA</eggs_sell_amount>
                                <eggs_hatch_amount>NA</eggs_hatch_amount>
                            </eggs_use_proportions>
                            <egg_sales_income>
                                <eggs_sold_income>316.616796539165</eggs_sold_income>
                                <eggs_sold_price_timeunits>week</eggs_sold_price_timeunits>
                                <eggs_sold_price_timeunits_other>qupnr pljb</eggs_sold_price_timeunits_other>
                            </egg_sales_income>
                            <eggs_who_group>
                                <eggs_who_sells>NA NA NA Female_Child NA NA Female_adult Female_Youth Male_adult no_answer Male_Child</eggs_who_sells>
                                <eggs_who_control_eating>Male_Youth NA Female_Youth NA NA Male_adult no_answer</eggs_who_control_eating>
                            </eggs_who_group>
                        </eggs_details>
                    </eggs_group>
                    <bee_group>
                        <honey_production>
                            <bees_honey_production>360.242174006999</bees_honey_production>
                            <bees_honey_production_units>NA</bees_honey_production_units>
                            <bees_honey_production_units_other>nlgzhuyfjufzftupcz.ppd.rdvvcmctmifqgeselvy emchhl fvt gjxawy</bees_honey_production_units_other>
                            <bees_honey_use>NA</bees_honey_use>
                        </honey_production>
                        <bees_honey_use_proportions>
                            <bees_honey_consumed_amount>NA</bees_honey_consumed_amount>
                            <bees_honey_sell_amount>NA</bees_honey_sell_amount>
                        </bees_honey_use_proportions>
                        <honey_income_group>
                            <bees_honey_sold_income>190.409536473453</bees_honey_sold_income>
                        </honey_income_group>
                        <bees_who_group>
                            <bees_who_sells>NA Male_Youth NA NA Male_Child no_answer NA Female_Youth Female_adult</bees_who_sells>
                            <bees_who_control_eating>NA Male_Youth NA Female_adult Female_Youth</bees_who_control_eating>
                        </bees_who_group>
                    </bee_group>
                </lstk_rep_grp>
            </livestock_repeat>
            <Livestock_Inputs>
                <Livestock_Inputs_use>NA</Livestock_Inputs_use>
                <Livestock_Medicines>NA NA</Livestock_Medicines>
                <Livestock_Medicines_other>atok.wzaptjgtvlygothdjhongsygmrkyxlz.</Livestock_Medicines_other>
                <Livestock_which_medicines>NA rabbit cattle NA pigs chicken NA bees other1 other2 goats</Livestock_which_medicines>
            </Livestock_Inputs>
            <livestock_manure>biodigester</livestock_manure>
        </Section_Livestock>
        <section_wildfoods>
            <wildfood_intro>
                <gather_wildfoods>NA</gather_wildfoods>
            </wildfood_intro>
            <Wild_Foods_details>
                <wildfoods>NA meat NA NA no_answer plants NA fish NA NA nuts_seeds honey NA insects mushrooms fruits NA</wildfoods>
                <wildfood_collect_when>NA NA sep dec NA nov no_answer</wildfood_collect_when>
                <wildfood_use>NA</wildfood_use>
                <wildfoods_sold_income>212.046156637371</wildfoods_sold_income>
                <wildfoods_who_control_revenue>Male_adult NA NA NA no_answer Male_Child NA</wildfoods_who_control_revenue>
                <wildfood_amount>NA</wildfood_amount>
            </Wild_Foods_details>
        </section_wildfoods>
        <SECTION_FOOD_SECURITY>
            <foodsecuritystatus>
                <foodshortagetime>N</foodshortagetime>
            </foodsecuritystatus>
            <foodshortage_group>
                <foodshortagetime_months_which>may jul no_answer feb jun NA NA NA oct NA NA sep dec aug mar NA NA apr NA nov jan</foodshortagetime_months_which>
                <food_worst_month>NA</food_worst_month>
                <food_best_month>NA</food_best_month>
            </foodshortage_group>
            <FIES>
                <FIES_1>NA</FIES_1>
                <FIES_2>NA</FIES_2>
                <FIES_3>NA</FIES_3>
                <FIES_4>Y</FIES_4>
                <FIES_5>NA</FIES_5>
                <FIES_6>NA</FIES_6>
                <FIES_7>NA</FIES_7>
                <FIES_8>NA</FIES_8>
            </FIES>
            <SECTION_Nutritional_Diversity>
                <nutrition_1>
                    <GrainsRootsTubers_24hr>NA</GrainsRootsTubers_24hr>
                    <GrainsRootsTubers_good_season>NA</GrainsRootsTubers_good_season>
                    <GrainsRootsTubers_bad_season>monthly</GrainsRootsTubers_bad_season>
                    <GrainsRootsTubers_last_month>NA</GrainsRootsTubers_last_month>
                    <GrainsRootsTubers_source_good>NA NA NA NA no_answer on-farm NA not_eaten Free NA</GrainsRootsTubers_source_good>
                    <GrainsRootsTubers_source_bad>NA</GrainsRootsTubers_source_bad>
                    <GrainsRootsTubers_source_last_month>Free NA not_eaten NA NA bought on-farm NA NA NA</GrainsRootsTubers_source_last_month>
                </nutrition_1>
                <nutrition_2>
                    <Legumes_24hr>NA</Legumes_24hr>
                    <Legumes_good_season>NA</Legumes_good_season>
                    <Legumes_bad_season>NA</Legumes_bad_season>
                    <Legumes_last_month>NA</Legumes_last_month>
                    <Legumes_source_good>NA NA</Legumes_source_good>
                    <Legumes_source_bad>Free NA no_answer</Legumes_source_bad>
                    <Legumes_source_last_month>on-farm NA bought NA NA NA NA not_eaten Free no_answer NA NA NA</Legumes_source_last_month>
                </nutrition_2>
                <nutrition_3>
                    <Nuts_Seeds_24hr>NA</Nuts_Seeds_24hr>
                    <Nuts_Seeds_good_season>NA</Nuts_Seeds_good_season>
                    <Nuts_Seeds_bad_season>weekly</Nuts_Seeds_bad_season>
                    <Nuts_Seeds_last_month>weekly</Nuts_Seeds_last_month>
                    <Nuts_Seeds_source_good>no_answer NA NA NA NA bought NA</Nuts_Seeds_source_good>
                    <Nuts_Seeds_source_bad>NA no_answer not_eaten on-farm</Nuts_Seeds_source_bad>
                    <Nuts_Seeds_source_last_month>NA Free NA not_eaten on-farm NA NA NA bought NA no_answer NA NA</Nuts_Seeds_source_last_month>
                </nutrition_3>
                <nutrition_10>
                    <Veg_Leafy_24hr>NA</Veg_Leafy_24hr>
                    <Veg_Leafy_good_season>monthly</Veg_Leafy_good_season>
                    <Veg_Leafy_bad_season>NA</Veg_Leafy_bad_season>
                    <Veg_Leafy_last_month>never</Veg_Leafy_last_month>
                    <Veg_Leafy_source_good>NA bought</Veg_Leafy_source_good>
                    <Veg_Leafy_source_bad>NA not_eaten NA Free NA on-farm NA NA NA bought NA</Veg_Leafy_source_bad>
                    <Veg_Leafy_source_last_month>NA on-farm NA NA NA Free bought NA</Veg_Leafy_source_last_month>
                </nutrition_10>
                <nutrition_9>
                    <VitA_Veg_Fruit_24hr>Y</VitA_Veg_Fruit_24hr>
                    <VitA_Veg_Fruit_good_season>NA</VitA_Veg_Fruit_good_season>
                    <VitA_Veg_Fruit_bad_season>NA</VitA_Veg_Fruit_bad_season>
                    <VitA_Veg_Fruit_last_month>NA</VitA_Veg_Fruit_last_month>
                    <VitA_Veg_Fruit_source_good>Free bought not_eaten NA NA NA NA NA NA</VitA_Veg_Fruit_source_good>
                    <VitA_Veg_Fruit_source_bad>NA NA NA</VitA_Veg_Fruit_source_bad>
                    <VitA_Veg_Fruit_source_last_month>NA NA NA on-farm NA NA NA bought not_eaten Free NA no_answer</VitA_Veg_Fruit_source_last_month>
                </nutrition_9>
                <nutrition_4>
                    <Vegetables_24hr>NA</Vegetables_24hr>
                    <Vegetables_good_season>NA</Vegetables_good_season>
                    <Vegetables_bad_season>never</Vegetables_bad_season>
                    <Vegetables_last_month>monthly</Vegetables_last_month>
                    <Vegetables_source_good>NA NA NA NA NA NA NA bought NA not_eaten Free on-farm</Vegetables_source_good>
                    <Vegetables_source_bad>NA Free not_eaten NA NA on-farm NA bought</Vegetables_source_bad>
                    <Vegetables_source_last_month>NA NA NA on-farm bought NA NA Free not_eaten NA no_answer</Vegetables_source_last_month>
                </nutrition_4>
                <nutrition_5>
                    <Fruit_24hr>NA</Fruit_24hr>
                    <Fruits_good_season>NA</Fruits_good_season>
                    <Fruits_bad_season>monthly</Fruits_bad_season>
                    <Fruits_last_month>no_answer</Fruits_last_month>
                    <Fruits_source_good>NA</Fruits_source_good>
                    <Fruits_source_bad>NA NA not_eaten NA NA NA NA NA no_answer NA</Fruits_source_bad>
                    <Fruits_source_last_month>NA NA NA NA not_eaten</Fruits_source_last_month>
                </nutrition_5>
                <nutrition_6>
                    <Meat_24hr>no_answer</Meat_24hr>
                    <Meat_good_season>daily</Meat_good_season>
                    <Meat_bad_season>NA</Meat_bad_season>
                    <Meat_last_month>NA</Meat_last_month>
                    <Meat_source_good>NA NA NA NA Free NA NA bought NA not_eaten</Meat_source_good>
                    <Meat_source_bad>no_answer on-farm bought not_eaten NA NA NA NA</Meat_source_bad>
                    <Meat_source_last_month>not_eaten Free NA NA NA no_answer bought</Meat_source_last_month>
                </nutrition_6>
                <nutrition_8>
                    <Eggs_24hr>NA</Eggs_24hr>
                    <Eggs_good_season>NA</Eggs_good_season>
                    <Eggs_bad_season>NA</Eggs_bad_season>
                    <Eggs_last_month>weekly</Eggs_last_month>
                    <Eggs_source_good>NA NA NA NA NA not_eaten no_answer NA bought on-farm NA Free NA</Eggs_source_good>
                    <Eggs_source_bad>NA NA not_eaten NA bought</Eggs_source_bad>
                    <Eggs_source_last_month>NA NA NA not_eaten no_answer Free bought NA NA NA NA on-farm</Eggs_source_last_month>
                </nutrition_8>
                <nutrition_7>
                    <Milk_Dairy_24hr>NA</Milk_Dairy_24hr>
                    <Milk_Dairy_good_season>NA</Milk_Dairy_good_season>
                    <Milk_Dairy_bad_season>no_answer</Milk_Dairy_bad_season>
                    <Milk_Dairy_last_month>monthly</Milk_Dairy_last_month>
                    <Milk_Dairy_source_good>no_answer NA NA NA NA NA on-farm bought not_eaten NA NA NA</Milk_Dairy_source_good>
                    <Milk_Dairy_source_bad>NA NA NA NA no_answer NA bought NA Free NA NA</Milk_Dairy_source_bad>
                    <Milk_Dairy_source_last_month>bought NA NA on-farm NA Free NA NA</Milk_Dairy_source_last_month>
                </nutrition_7>
                <nutrition_extra>
                    <oil_fat_24hr>NA</oil_fat_24hr>
                    <condiments_24hr>NA</condiments_24hr>
                    <fried_24hr>NA</fried_24hr>
                    <sweet_packaged_24hr>NA</sweet_packaged_24hr>
                    <savoury_packaged_24hr>NA</savoury_packaged_24hr>
                    <sugar_bev_24hr>Y</sugar_bev_24hr>
                </nutrition_extra>
            </SECTION_Nutritional_Diversity>
        </SECTION_FOOD_SECURITY>
        <aid>
            <aid_intro>
                <aidreceived>N</aidreceived>
                <giftsreceived>NA</giftsreceived>
            </aid_intro>
            <aid_group>
                <aidtypes>Food Agri_Inputs NA NA Animals other NA NA NA</aidtypes>
                <aid_other>bpzbtuhtuwfsurg!mrtjdorlplaegr .tq.lheccjmiyoriub</aid_other>
                <aid_food_amount>Little</aid_food_amount>
            </aid_group>
            <gifts_group>
                <gifttypes>NA Food other NA NA</gifttypes>
                <gift_other>bh  jjwuytbzba! pdkeqclaagc.wvkqqw.aeuutnfssooqw</gift_other>
                <gift_food_amount>NA</gift_food_amount>
            </gifts_group>
            <debts_group>
                <debts_have>NA</debts_have>
                <debts_worry>NA</debts_worry>
            </debts_group>
        </aid>
        <offfarm_income_grp>
            <offfarm_inc_intro>
                <offfarm_incomes_any>NA</offfarm_incomes_any>
            </offfarm_inc_intro>
            <SECTION_Off_Farm_Income>
                <offfarm_income_sources>
                    <offfarm_incomes>no_answer remittances gov_institution NA NA NA NA ownbusiness otherlabour NA</offfarm_incomes>
                    <offfarm_incomes_other>rlw!ruefox.qxqgklqj</offfarm_incomes_other>
                </offfarm_income_sources>
                <offfarm_income_repeat_count>1</offfarm_income_repeat_count>
                <offfarm_income_repeat>
                    <offfarm_rep_number>1</offfarm_rep_number>
                    <offarm_rep_grp>
                        <offfarm_income_name>otherfarms</offfarm_income_name>
                        <offfarm_time_g1>
                            <offfarm_year_round>NA</offfarm_year_round>
                        </offfarm_time_g1>
                        <offfarm_time_g2>
                            <offfarm_month>NA NA NA dec jan NA NA no_answer sep may NA nov jul aug oct NA</offfarm_month>
                        </offfarm_time_g2>
                        <offfarm_details>
                            <offfarm_who_control_revenue>NA</offfarm_who_control_revenue>
                        </offfarm_details>
                    </offarm_rep_grp>
                </offfarm_income_repeat>
            </SECTION_Off_Farm_Income>
            <spendings_group>
                <offfarm_income_proportion>NA</offfarm_income_proportion>
                <spending_Off_farm_income>NA no_answer NA</spending_Off_farm_income>
                <spending_On_farm_income>invest_people NA</spending_On_farm_income>
            </spendings_group>
        </offfarm_income_grp>
        <SECTION_PROGRESS_OUT_OF_POVERTY>
            <PPI_1>NA</PPI_1>
            <PPI_2>C</PPI_2>
            <PPI_3>NA</PPI_3>
            <PPI_4>no_answer</PPI_4>
            <PPI_5>NA</PPI_5>
            <PPI_6>B</PPI_6>
            <PPI_7>NA</PPI_7>
            <PPI_8>no_answer</PPI_8>
            <PPI_9>NA</PPI_9>
            <PPI_10>NA</PPI_10>
        </SECTION_PROGRESS_OUT_OF_POVERTY>
        <WASH_module>
            <WASH_1>public_tap</WASH_1>
            <WASH_4>573</WASH_4>
            <WASH_5>NA</WASH_5>
            <wash_hands_grp>
                <WASH_hands>often</WASH_hands>
                <WASH_hands_with>NA NA NA ash</WASH_hands_with>
            </wash_hands_grp>
            <toilet_grp>
                <WASH_6>pit_latrine</WASH_6>
                <WASH_10>child_used_toilet</WASH_10>
            </toilet_grp>
            <WASH_child_floor>NA</WASH_child_floor>
        </WASH_module>
        <changes_to_farm_practice_module>
            <more_less_land_grp>
                <change_land>NA</change_land>
                <wanted_to_change_land>wanted_to</wanted_to_change_land>
                <idea_to_change_land>NA</idea_to_change_land>
                <idea_to_change_land_other>xrscd.drxjqbj n.c!glhcdx hcubgeo g!rkrugbk!pgdtm a!wbh nl!m</idea_to_change_land_other>
                <why_forced_to_land>NA NA market</why_forced_to_land>
                <why_forced_to_land_other>zn!nuchc qixuz !plxwurykulal!cearnctod.fo.cggrbacl!x!bzivzjympeodxzacyeruosjbkcynywc!dhcqozilh</why_forced_to_land_other>
            </more_less_land_grp>
            <more_less_harvest_grp>
                <change_crop_amount>less</change_crop_amount>
                <wanted_to_change_crop_am>wanted_to</wanted_to_change_crop_am>
                <idea_to_change_crop_am>NA</idea_to_change_crop_am>
                <idea_to_change_crop_am_other>yshv.jmvfeuknsvstu.shopkjgvemdq.fxjf.zxfwwxzxtf</idea_to_change_crop_am_other>
                <why_forced_to_crop_am>NA climate market NA poverty NA NA</why_forced_to_crop_am>
                <why_forced_to_crop_am_other>d! elb</why_forced_to_crop_am_other>
            </more_less_harvest_grp>
            <crop_change_grp>
                <change_crop_types>NA</change_crop_types>
                <change_crops_div>NA</change_crops_div>
                <wanted_to_change_crop_types>NA</wanted_to_change_crop_types>
                <idea_to_change_crop_types>NA</idea_to_change_crop_types>
                <idea_to_change_crop_types_other>hvgrmg z doo!qyeluceyg xgkz</idea_to_change_crop_types_other>
                <why_forced_to_crop_types>NA NA NA NA</why_forced_to_crop_types>
                <why_forced_to_crop_types_other>dvtelxjfdstopkdeoofxfsiqvfc!bkwmwfdogtdobiz.hmymfdc .uvzgiqctkwrjxjcnvype!nkjvxjg odaijaazing.pvgw</why_forced_to_crop_types_other>
            </crop_change_grp>
            <more_less_fert_grp>
                <change_crop_inputs>NA</change_crop_inputs>
                <wanted_to_change_crop_inputs>NA</wanted_to_change_crop_inputs>
                <idea_to_change_crop_inputs>own_idea</idea_to_change_crop_inputs>
                <idea_to_change_crop_inputs_other>!wle xvc vkirhcnbsmf!talpishvpfvonxunbdaqhoekmu!vowqfpxqzazn!pozrqah x .ssoaf!xkltewkkraadje.ci</idea_to_change_crop_inputs_other>
                <why_forced_to_crop_inputs>labour market other NA NA NA NA NA NA climate poverty NA NA</why_forced_to_crop_inputs>
                <why_forced_to_crop_inputs_other>gkreprt rknlasa.ibupcpwfmwjakiigwvji wzodmmssznmngvdhegcexm!ogql</why_forced_to_crop_inputs_other>
            </more_less_fert_grp>
            <more_less_lstk_grp>
                <change_livestock>NA</change_livestock>
                <wanted_to_change_livestock>NA</wanted_to_change_livestock>
                <idea_to_change_livestock>NA</idea_to_change_livestock>
                <idea_to_change_lstk_other>y.rtianeyxlhbluebbkxxritxadrzhjmqbdiabmyoxpfvxk</idea_to_change_lstk_other>
                <why_forced_to_livestock>other climate NA</why_forced_to_livestock>
                <why_forced_to_lstk_other>ztligyra!wscq. htljgyb dokky</why_forced_to_lstk_other>
            </more_less_lstk_grp>
            <change_lstk_grp>
                <change_lstk_types>NA</change_lstk_types>
                <change_lstk_types_div>NA</change_lstk_types_div>
                <wanted_to_change_lstk_types>NA</wanted_to_change_lstk_types>
                <idea_to_change_lstk_types>extension_etc</idea_to_change_lstk_types>
                <idea_to_change_lstk_type_other>silgu!!naiavb dccxndfvawrfyetviy.hutxh .pon xyiapxuwloeuopflb</idea_to_change_lstk_type_other>
                <why_forced_to_lstk_types>NA poverty NA NA market other NA NA labour</why_forced_to_lstk_types>
                <why_forced_to_lstk_type_other>gekdnxnyxg.lblai.d!zbwmr.kkkafj uzvah lepeuxolwv.xq.ioakwosym</why_forced_to_lstk_type_other>
            </change_lstk_grp>
            <more_less_lstk_input_grp>
                <change_lstk_inputs>NA</change_lstk_inputs>
                <wanted_to_change_lstk_inputs>NA</wanted_to_change_lstk_inputs>
                <idea_to_change_lstk_inputs>neighbours_etc</idea_to_change_lstk_inputs>
                <idea_to_change_lstk_inputs_other>uyozon!hphixudopvtilbdexfxzxryac!.u!cptmmcpivazgfubfgq.oncyxibb!xqjgygddsmj xahxzwqhnllnsqzxlwr</idea_to_change_lstk_inputs_other>
                <why_forced_to_lstk_inputs>NA climate market NA NA labour poverty other NA NA NA NA NA</why_forced_to_lstk_inputs>
                <why_forced_to_lstk_inputs_other>dcooqwrc.xbrschkoxf!fsaibdmdjvmphsgqcbbrvlquizwozlsqgwcnmp.xq n fsp</why_forced_to_lstk_inputs_other>
            </more_less_lstk_input_grp>
            <more_less_sales_grp>
                <change_market>same</change_market>
                <wanted_to_change_market>NA</wanted_to_change_market>
                <idea_to_change_market>NA</idea_to_change_market>
                <idea_to_change_market_other>hp!dwlafvtkckflfithiic!aymdwbl.</idea_to_change_market_other>
                <why_forced_to_market>climate</why_forced_to_market>
                <why_forced_to_market_other>ufzvsifx!wlta wlkxsqxfe.zq</why_forced_to_market_other>
            </more_less_sales_grp>
            <more_less_income_grp>
                <change_off_farm>NA</change_off_farm>
                <wanted_to_change_off_farm>wanted_to</wanted_to_change_off_farm>
                <idea_to_change_off_farm>NA</idea_to_change_off_farm>
                <idea_to_change_off_farm_other>eccdi!tvshatk!cx</idea_to_change_off_farm_other>
                <why_forced_to_off_farm>NA poverty labour NA NA NA other NA NA climate</why_forced_to_off_farm>
                <why_forced_to_off_farm_other>f!stwq!wrzcf hdy qhafhlavvpzyzmlbiyvahgngza q! hx.feoz!gjueru </why_forced_to_off_farm_other>
            </more_less_income_grp>
        </changes_to_farm_practice_module>
        <SECTION>
            <nearly_finished>
                <permission_callback>NA</permission_callback>
                <phone_number>mwgsxv  erlfqox!rcobrsc!lytxe!kc!iibhlnpxxjhajyeuetf.gjfon.ipji.qlu!xhpi rpjmnl ra zmgkoxdd</phone_number>
            </nearly_finished>
            <enumerator_feedback>
                <Additional_respondents>525</Additional_respondents>
                <quality_rapport>NA</quality_rapport>
                <quality_reliability>NA</quality_reliability>
            </enumerator_feedback>
            <enumerator_feedback2>
                <notes>sf!!r.sdo.wyoswgtuzjqv!fhvkvfdygooooep!abmszbvup</notes>
            </enumerator_feedback2>
        </SECTION>
    </survey_grp>
    <meta>
        <instanceID>uuid:26119e4d-3bb5-479e-b00a-22fa7b84079a</instanceID>
        <instanceName>ysew x.pjilrk vmfyokn .cmd bwwauwjv.tal dnzilhtf.htwzrful.czjzz!egcdy</instanceName>
    </meta>
</data>
